{
  "id": "236164572",
  "link": "https://emumo.xiami.com/album/236164572",
  "name": "即兴表演",
  "photo_url": "https://pic.xiami.net/images/album/img34/1983717034/2361645721436164572.jpg@4e_1c_100Q_185w_185h",
  "artist_name": "牙牙乐",
  "languages": [
    "国语"
  ],
  "companies": [
    ""
  ],
  "published_date": [
    "2015年07月03日"
  ],
  "categories": [
    "EP",
    "单曲"
  ],
  "play_count_num": 18862,
  "favorite_count_num": 38,
  "comments_num": 0,
  "intro": "创作歌手牙牙乐和赵芷彤最新合唱单曲《即兴表演》，7月正式上线",
  "songs": [
    {
      "name": "即兴表演",
      "link": "https://emumo.xiami.com/song/xLB30X1674b"
    }
  ],
  "comments": []
}