{
  "id": "310862",
  "name": "You Are There",
  "link": "https://emumo.xiami.com/album/310862",
  "photo_url": "https://pic.xiami.net/images/album/img2/6902/3108621335338117.jpg@4e_1c_100Q_185w_185h",
  "artist_name": "MONO",
  "languages": [
    "其他"
  ],
  "companies": [
    "Temporary Residence"
  ],
  "published_date": [
    "2006年04月06日"
  ],
  "categories": [
    "录音室专辑"
  ],
  "styles": [
    "后摇 Post-Rock"
  ],
  "play_count_num": 349065,
  "favorite_count_num": 1544,
  "comments_num": 95,
  "intro": "<p>2000年成立，2006年发行第四张专辑，在后摇界里Mono也可以算是高产了。新专辑《You Are There》延续了上作《Walking Cloud and Deep Red Sky, Flag Fluttered and the Sun Shined》的风格走向，没有了《One Step More And You Die》时期偏执狂似的爆发，也不再象《Under The Pipal Tree》那么甜美，氛围大气得令人迷醉。袁智聪先生说过Mogwai是典型的Quiet-Loud-Quiet结构，那Mono又何尝不是？长篇的作品没有令人失望，完全地凸现了他们大气的特点。在“The Flames Beyond The Cold Mountain”里对安静和爆发时机的掌握恰到好处，而“A Heart Has Asked For The Pleasure”的爆发则来得更突然、更猛烈一些。(转自eMule)</p><p></p><p> Throughout their six-year career, this Japanese quartet has ascended consistently in both popularity and critical acclaim. But still elusive is the successful translation of their powerful and violently beautiful live performances to their recordings, until now. Once again recorded by Steve Albini, the album extends the cinematic drama of 2003's &amp;Walking Cloud And Deep Red Sky, Flag Fluttered And The Sun Shined&amp; while surpassing the sinister heaviness of 2002's lauded &amp;One Step More And You Die&amp;. If &amp;Walking Cloud&amp; was a nuclear winter, then &amp;You Are There&amp; is the post-war rebirth. This band isn't heavy like Black Sabbath. They're heavy like Beethoven. </p>",
  "songs": [
    {
      "name": "The Flames Beyond The Cold Mountain",
      "link": "https://emumo.xiami.com/song/dCoMJ2b6c8"
    },
    {
      "name": "A heart has asked for the pleasure",
      "link": "https://emumo.xiami.com/song/cqtSgec799"
    },
    {
      "name": "Yearning",
      "link": "https://emumo.xiami.com/song/UyX38e424"
    },
    {
      "name": "Are you there?",
      "link": "https://emumo.xiami.com/song/UyX48a406"
    },
    {
      "name": "The remains of the day",
      "link": "https://emumo.xiami.com/song/bAwzP15c45"
    },
    {
      "name": "Moonlight",
      "link": "https://emumo.xiami.com/song/UyX650f44"
    }
  ],
  "comments": [
    {
      "author": {
        "id": "3707446",
        "name": "虾米用户",
        "motto": "我还没想好要写什么...",
        "link": "https://emumo.xiami.com/u/3707446",
        "photo_url": "https://pic.xiami.net/images/avatar_new/74/5e838fe536c85_3707446_1585680357.jpg@1e_1c_0i_1o_100Q_100w_100h"
      },
      "time": "2020-01-21 07:06",
      "ageree_num": 0,
      "disageree_num": 0,
      "brief": "那天我去的时候我前面的人买了最后一张这，她打开碟盒，我感觉上面的小天使在苦笑：）                     <br><br><a href=\"//emumo.xiami.com/apps/mobile\" target=\"_blank\">来自iPhone客户端</a>",
      "replies": []
    },
    {
      "author": {
        "id": "426752259",
        "name": "虾米用户",
        "motto": "",
        "link": "https://emumo.xiami.com/u/426752259",
        "photo_url": "https://pic.xiami.net/images/avatar_new/798524758_1561945746.jpg@1e_1c_0i_1o_100Q_100w_100h"
      },
      "time": "2019-12-03 23:52",
      "ageree_num": 1,
      "disageree_num": 0,
      "brief": "mono这几张专辑真的是张张经典。从曲子到封面，难以言表。用心去听吧。",
      "replies": []
    },
    {
      "author": {
        "id": "7539949",
        "name": "虾米用户",
        "motto": "隨心而活",
        "link": "https://emumo.xiami.com/u/7539949",
        "photo_url": "https://pic.xiami.net/images/avatar_new/150/7539949_1404979886.jpg@1e_1c_0i_1o_100Q_100w_100h"
      },
      "time": "2019-11-24 14:28",
      "ageree_num": 0,
      "disageree_num": 0,
      "brief": "感觉看了一场电影～",
      "replies": []
    },
    {
      "author": {
        "id": "377345793",
        "name": "虾米用户",
        "motto": "我贴在地面步行，不在云端...",
        "link": "https://emumo.xiami.com/u/377345793",
        "photo_url": "https://pic.xiami.net/images/avatar_new/7546/5d7cfa12eb5ce_377345793_b_w240h240.png@1e_1c_0i_1o_100Q_100w_100h"
      },
      "time": "2019-07-27 04:16",
      "ageree_num": 0,
      "disageree_num": 0,
      "brief": "青木森林                     <br><br><a href=\"//emumo.xiami.com/apps/mobile\" target=\"_blank\">来自android客户端</a>",
      "replies": []
    },
    {
      "author": {
        "id": "12765269",
        "name": "虾米用户",
        "motto": "",
        "link": "https://emumo.xiami.com/u/12765269",
        "photo_url": "https://pic.xiami.net/images/user/12765269/db7f6e8e1ccc4a44b76ec8bd3e270053_3aa895632c8d48b48b946deeb60ec76d.jpg@1e_1c_0i_1o_100Q_100w_100h"
      },
      "time": "2019-05-13 00:16",
      "ageree_num": 0,
      "disageree_num": 0,
      "brief": "入门砖",
      "replies": []
    },
    {
      "author": {
        "id": "6984513",
        "name": "虾米用户",
        "motto": "",
        "link": "https://emumo.xiami.com/u/6984513",
        "photo_url": "https://pic.xiami.net/images/user/6984513/d84b218d4b4d428d93a957ba8006baf7_71866069379c4e1386a9cc05379db953.jpg@1e_1c_0i_1o_100Q_100w_100h"
      },
      "time": "2019-01-02 20:52",
      "ageree_num": 0,
      "disageree_num": 0,
      "brief": "特别喜欢                     <br><br><a href=\"//emumo.xiami.com/apps/mobile\" target=\"_blank\">来自android客户端</a>",
      "replies": []
    },
    {
      "author": {
        "id": "3583995",
        "name": "虾米用户",
        "motto": "一個人的戰爭",
        "link": "https://emumo.xiami.com/u/3583995",
        "photo_url": "https://pic.xiami.net/images/avatar_new/71/67/3583995/3583995_1306455728.gif@1e_1c_0i_1o_100Q_100w_100h"
      },
      "time": "2018-12-26 21:41",
      "ageree_num": 0,
      "disageree_num": 0,
      "brief": ".                     <br><br><a href=\"//emumo.xiami.com/apps/mobile\" target=\"_blank\">来自iPhone客户端</a>",
      "replies": []
    },
    {
      "author": {
        "id": "42963872",
        "name": "虾米用户",
        "motto": "我还没想好要写什么...",
        "link": "https://emumo.xiami.com/u/42963872",
        "photo_url": "https://pic.xiami.net/images/avatar_new/859/5c0fa8d9c0a15_42963872_1544530137.jpg@1e_1c_0i_1o_100Q_100w_100h"
      },
      "time": "2018-12-13 22:28",
      "ageree_num": 0,
      "disageree_num": 0,
      "brief": "-                     <br><br><a href=\"//emumo.xiami.com/apps/mobile\" target=\"_blank\">来自iPhone客户端</a>",
      "replies": []
    },
    {
      "author": {
        "id": "402446344",
        "name": "虾米用户",
        "motto": "",
        "link": "https://emumo.xiami.com/u/402446344",
        "photo_url": "https://pic.xiami.net/images/default/xiami_8/avatar_new_3x.png@1e_1c_0i_1o_100Q_100w_100h"
      },
      "time": "2018-08-28 04:56",
      "ageree_num": 2,
      "disageree_num": 0,
      "brief": "2018.8.27.失眠。很多年以后我会不会记得今天这个夜晚。孤独。我甚至想过不如就从这18楼跳下去好了。不知道很多年以后我还会不会这样想。我们永远困在时间与空间中。                     <br><br><a href=\"//emumo.xiami.com/apps/mobile\" target=\"_blank\">来自android客户端</a>",
      "replies": []
    },
    {
      "author": {
        "id": "191482885",
        "name": "虾米用户",
        "motto": "",
        "link": "https://emumo.xiami.com/u/191482885",
        "photo_url": "https://pic.xiami.net/images/default/xiami_8/avatar_new_3x.png@1e_1c_0i_1o_100Q_100w_100h"
      },
      "time": "2018-07-23 20:06",
      "ageree_num": 1,
      "disageree_num": 0,
      "brief": "<br><br><a href=\"//emumo.xiami.com/apps/mobile\" target=\"_blank\">来自android客户端</a>",
      "replies": []
    },
    {
      "author": {
        "id": "294410947",
        "name": "虾米用户",
        "motto": "",
        "link": "https://emumo.xiami.com/u/294410947",
        "photo_url": "https://pic.xiami.net/images/avatar_new/5888/5b1fc3a78cd54_294410947_b_w240h240.png@1e_1c_0i_1o_100Q_100w_100h"
      },
      "time": "2018-06-09 13:42",
      "ageree_num": 0,
      "disageree_num": 0,
      "brief": "太喜欢这张了 <br><br><a href=\"//emumo.xiami.com/apps/mobile\" target=\"_blank\">来自android客户端</a>",
      "replies": []
    },
    {
      "author": {
        "id": "260123122",
        "name": "虾米用户",
        "motto": " ",
        "link": "https://emumo.xiami.com/u/260123122",
        "photo_url": "https://pic.xiami.net/images/avatar_new/5202/5ec92d40df725_260123122_1590242624.jpg@1e_1c_0i_1o_100Q_100w_100h"
      },
      "time": "2018-03-16 16:13",
      "ageree_num": 0,
      "disageree_num": 0,
      "brief": "/ <br><br><a href=\"//emumo.xiami.com/apps/mobile\" target=\"_blank\">来自iPhone客户端</a>",
      "replies": []
    },
    {
      "author": {
        "id": "350020031",
        "name": "虾米用户",
        "motto": "",
        "link": "https://emumo.xiami.com/u/350020031",
        "photo_url": "https://pic.xiami.net/images/user/350020031/8d599c24bcc64ca6a290bb1e8ecf4d96_613fbf3304fe4a7bba50adf406dfe659.jpg@1e_1c_0i_1o_100Q_100w_100h"
      },
      "time": "2018-02-25 22:51",
      "ageree_num": 0,
      "disageree_num": 0,
      "brief": "最爱的两个专之一 <br><br><a href=\"//emumo.xiami.com/apps/mobile\" target=\"_blank\">来自android客户端</a>",
      "replies": []
    },
    {
      "author": {
        "id": "50708145",
        "name": "虾米用户",
        "motto": "讓流水過。",
        "link": "https://emumo.xiami.com/u/50708145",
        "photo_url": "https://pic.xiami.net/images/avatar_new/1014/5b650f169e041_50708145_1533349654.jpg@1e_1c_0i_1o_100Q_100w_100h"
      },
      "time": "2018-01-24 23:26",
      "ageree_num": 0,
      "disageree_num": 0,
      "brief": ". <br><br><a href=\"//emumo.xiami.com/apps/mobile\" target=\"_blank\">来自iPhone客户端</a>",
      "replies": []
    },
    {
      "author": {
        "id": "17326367",
        "name": "虾米用户",
        "motto": "爱就是极快速的能量振动",
        "link": "https://emumo.xiami.com/u/17326367",
        "photo_url": "https://pic.xiami.net/images/artistlogo/16/15558178028616.jpg@1e_1c_0i_1o_100Q_100w_100h"
      },
      "time": "2017-12-01 16:57",
      "ageree_num": 0,
      "disageree_num": 0,
      "brief": "混乱无比，3星/5星",
      "replies": []
    },
    {
      "author": {
        "id": "47762018",
        "name": "虾米用户",
        "motto": "虾米我永远爱你",
        "link": "https://emumo.xiami.com/u/47762018",
        "photo_url": "https://pic.xiami.net/images/user/47762018/45ba5b79cef145ea831f7e84724155ba_5660dd12744c48a89efdefba50b542b6.jpg@1e_1c_0i_1o_100Q_100w_100h"
      },
      "time": "2017-08-29 23:13",
      "ageree_num": 0,
      "disageree_num": 0,
      "brief": "~ <br><br><a href=\"//emumo.xiami.com/apps/mobile\" target=\"_blank\">来自android客户端</a>",
      "replies": []
    },
    {
      "author": {
        "id": "238300984",
        "name": "虾米用户",
        "motto": "世界很大 时间太少",
        "link": "https://emumo.xiami.com/u/238300984",
        "photo_url": "https://pic.xiami.net/images/avatar_new/4766/5ab918ae5d27e_238300984_1522079918.jpg@1e_1c_0i_1o_100Q_100w_100h"
      },
      "time": "2017-03-08 23:29",
      "ageree_num": 0,
      "disageree_num": 0,
      "brief": "真正感受到后摇的情绪震撼是从这张专辑开始 <br><br><a href=\"//emumo.xiami.com/apps/mobile\" target=\"_blank\">来自iPhone客户端</a>",
      "replies": []
    },
    {
      "author": {
        "id": "122670826",
        "name": "虾米用户",
        "motto": "我还没想好要写什么...",
        "link": "https://emumo.xiami.com/u/122670826",
        "photo_url": "https://pic.xiami.net/images/avatar_new/2453/5e889a6f39f5d_122670826_1586010735.jpg@1e_1c_0i_1o_100Q_100w_100h"
      },
      "time": "2016-11-22 22:34",
      "ageree_num": 0,
      "disageree_num": 0,
      "brief": "<img src=\"//img.xiami.net/res/js/jquery/editor/sets/bbcode/images/smilies/default/412.png\"> <br><br><a href=\"//emumo.xiami.com/apps/mobile\" target=\"_blank\">来自android客户端</a>",
      "replies": []
    },
    {
      "author": {
        "id": "9756829",
        "name": "虾米用户",
        "motto": "我还没想好要写什么...",
        "link": "https://emumo.xiami.com/u/9756829",
        "photo_url": "https://pic.xiami.net/images/avatar_new/195/560eb6c9a72c5_9756829_1443804873.png@1e_1c_0i_1o_100Q_100w_100h"
      },
      "time": "2016-07-18 12:24",
      "ageree_num": 1,
      "disageree_num": 0,
      "brief": "要哭了 <br><br><a href=\"//emumo.xiami.com/apps/mobile\" target=\"_blank\">来自android客户端</a>",
      "replies": []
    },
    {
      "author": {
        "id": "51397158",
        "name": "虾米用户",
        "motto": "DeathContinu",
        "link": "https://emumo.xiami.com/u/51397158",
        "photo_url": "https://pic.xiami.net/images/avatar_new/1027/51397158_1564544083.jpeg@1e_1c_0i_1o_100Q_100w_100h"
      },
      "time": "2016-05-27 15:51",
      "ageree_num": 0,
      "disageree_num": 0,
      "brief": "原盘已收！",
      "replies": []
    },
    {
      "author": {
        "id": "48628377",
        "name": "虾米用户",
        "motto": "先有若风后有天",
        "link": "https://emumo.xiami.com/u/48628377",
        "photo_url": "https://pic.xiami.net/images/avatar_new/972/48628377_1427963619.jpg@1e_1c_0i_1o_100Q_100w_100h"
      },
      "time": "2016-03-13 00:22",
      "ageree_num": 0,
      "disageree_num": 0,
      "brief": "今晚完整听完这张专辑，第一反应是想去看一次极光。mono什么时候能再来中国？",
      "replies": []
    },
    {
      "author": {
        "id": "38761607",
        "name": "虾米用户",
        "motto": "我还没想好要写什么...",
        "link": "https://emumo.xiami.com/u/38761607",
        "photo_url": "https://pic.xiami.net/images/avatar_new/775/5cd4334665cb6_38761607_1557410630.jpg@1e_1c_0i_1o_100Q_100w_100h"
      },
      "time": "2016-02-21 11:19",
      "ageree_num": 0,
      "disageree_num": 0,
      "brief": "下雨天就适合躲在被窝听歌～",
      "replies": []
    },
    {
      "author": {
        "id": "6975678",
        "name": "虾米用户",
        "motto": "生命如此短暂我比烟花灿烂",
        "link": "https://emumo.xiami.com/u/6975678",
        "photo_url": "https://pic.xiami.net/images/avatar_new/139/6975678_1517753054.png@1e_1c_0i_1o_100Q_100w_100h"
      },
      "time": "2015-11-15 16:49",
      "ageree_num": 1,
      "disageree_num": 0,
      "brief": "神秘主义的狂欢",
      "replies": []
    },
    {
      "author": {
        "id": "6053083",
        "name": "虾米用户",
        "motto": "很不高兴为您服务",
        "link": "https://emumo.xiami.com/u/6053083",
        "photo_url": "https://pic.xiami.net/images/avatar_new/121/5b779074982f3_6053083_1534562420.jpg@1e_1c_0i_1o_100Q_100w_100h"
      },
      "time": "2015-11-11 02:46",
      "ageree_num": 0,
      "disageree_num": 0,
      "brief": "2:45 <br><br><a href=\"//emumo.xiami.com/apps/mobile\" target=\"_blank\">来自iPhone客户端</a>",
      "replies": []
    },
    {
      "author": {
        "id": "962072",
        "name": "虾米用户",
        "motto": "",
        "link": "https://emumo.xiami.com/u/962072",
        "photo_url": "https://pic.xiami.net/images/default/xiami_8/avatar_new_3x.png@1e_1c_0i_1o_100Q_100w_100h"
      },
      "time": "2015-10-10 08:28",
      "ageree_num": 1,
      "disageree_num": 0,
      "brief": "气温骤降的时候听这碟是十分惬意的",
      "replies": []
    },
    {
      "author": {
        "id": "32362730",
        "name": "虾米用户",
        "motto": "5はいいぞ~~",
        "link": "https://emumo.xiami.com/u/32362730",
        "photo_url": "https://pic.xiami.net/images/avatar_new/647/5fcdedc963ea4_32362730_1607331273.jpg@1e_1c_0i_1o_100Q_100w_100h"
      },
      "time": "2015-08-23 15:52",
      "ageree_num": 0,
      "disageree_num": 0,
      "brief": "(•̀⌄•́) <br><br><a href=\"//emumo.xiami.com/apps/mobile\" target=\"_blank\">来自iPhone客户端</a>",
      "replies": []
    },
    {
      "author": {
        "id": "50102067",
        "name": "虾米用户",
        "motto": " ",
        "link": "https://emumo.xiami.com/u/50102067",
        "photo_url": "https://pic.xiami.net/images/avatar_new/1002/5711bc8e30719_50102067_1460780174.jpg@1e_1c_0i_1o_100Q_100w_100h"
      },
      "time": "2015-06-22 10:38",
      "ageree_num": 0,
      "disageree_num": 0,
      "brief": "最喜欢这张专辑。<br>记得那年的夏夜，IPOD里面循环地听这张专辑，居然听出了阵阵寒意，泪流不止",
      "replies": []
    },
    {
      "author": {
        "id": "1914083",
        "name": "虾米用户",
        "motto": "",
        "link": "https://emumo.xiami.com/u/1914083",
        "photo_url": "https://pic.xiami.net/images/avatar_new/38/28/1914083/1914083_1305953903.jpg@1e_1c_0i_1o_100Q_100w_100h"
      },
      "time": "2015-06-22 00:30",
      "ageree_num": 1,
      "disageree_num": 0,
      "brief": "无论听多少次都是泪流满面",
      "replies": []
    },
    {
      "author": {
        "id": "37176998",
        "name": "虾米用户",
        "motto": "",
        "link": "https://emumo.xiami.com/u/37176998",
        "photo_url": "https://pic.xiami.net/images/default/xiami_8/avatar_new_3x.png@1e_1c_0i_1o_100Q_100w_100h"
      },
      "time": "2015-04-02 16:55",
      "ageree_num": 0,
      "disageree_num": 0,
      "brief": "人类的故事，你的故事，是不是也是我的故事",
      "replies": []
    },
    {
      "author": {
        "id": "7732508",
        "name": "虾米用户",
        "motto": "生是過客 跋涉虛無之境",
        "link": "https://emumo.xiami.com/u/7732508",
        "photo_url": "https://pic.xiami.net/images/avatar_new/154/5d1eaa1aceeee_7732508_1562290714.jpg@1e_1c_0i_1o_100Q_100w_100h"
      },
      "time": "2015-03-18 15:17",
      "ageree_num": 1,
      "disageree_num": 0,
      "brief": "星空 落雪 岩漿 黑石 綠野  <br><br><a href=\"//emumo.xiami.com/apps/mobile\" target=\"_blank\">来自iPhone客户端</a>",
      "replies": []
    },
    {
      "author": {
        "id": "10695504",
        "name": "虾米用户",
        "motto": " ",
        "link": "https://emumo.xiami.com/u/10695504",
        "photo_url": "https://pic.xiami.net/images/avatar_new/213/59d673b8d9286_10695504_1507226552.jpg@1e_1c_0i_1o_100Q_100w_100h"
      },
      "time": "2015-02-07 17:45",
      "ageree_num": 5,
      "disageree_num": 0,
      "brief": "download<br><a href=\"http://weibo.com/5061412684/BesousTb8\" target=\"_blank\" rel=\"nofollow noreferrer noopener\">http://weibo.com/5061412684/BesousTb8</a>",
      "replies": []
    },
    {
      "author": {
        "id": "2104019",
        "name": "虾米用户",
        "motto": "",
        "link": "https://emumo.xiami.com/u/2104019",
        "photo_url": "https://pic.xiami.net/images/avatar_new/42/8/2104019/2104019_1311815892.jpg@1e_1c_0i_1o_100Q_100w_100h"
      },
      "time": "2015-01-07 22:17",
      "ageree_num": 0,
      "disageree_num": 0,
      "brief": "很爱很爱这张专辑啊，无论是里面的曲子，还是封面… <br><br><a href=\"//emumo.xiami.com/apps/mobile\" target=\"_blank\">来自android客户端</a>",
      "replies": []
    },
    {
      "author": {
        "id": "26070224",
        "name": "虾米用户",
        "motto": "你不要吃我，我唱好听的歌...",
        "link": "https://emumo.xiami.com/u/26070224",
        "photo_url": "https://pic.xiami.net/images/avatar_new/521/26070224_1427042234.jpg@1e_1c_0i_1o_100Q_100w_100h"
      },
      "time": "2014-11-23 22:38",
      "ageree_num": 0,
      "disageree_num": 0,
      "brief": "还是喜欢 <br><br><a href=\"//emumo.xiami.com/apps/mobile\" target=\"_blank\">来自android客户端</a>",
      "replies": []
    },
    {
      "author": {
        "id": "35210469",
        "name": "虾米用户",
        "motto": "我还没想好要写什么...",
        "link": "https://emumo.xiami.com/u/35210469",
        "photo_url": "https://pic.xiami.net/images/avatar_new/704/5c051ce18238b_35210469_1543838945.jpg@1e_1c_0i_1o_100Q_100w_100h"
      },
      "time": "2014-11-18 20:57",
      "ageree_num": 0,
      "disageree_num": 0,
      "brief": "封面好美 <br><br><a href=\"//emumo.xiami.com/apps/mobile\" target=\"_blank\">来自iPhone客户端</a>",
      "replies": [
        {
          "author": {
            "id": "47012091",
            "name": "虾米用户",
            "motto": "欧美控，冷门癖",
            "link": "https://emumo.xiami.com/u/47012091",
            "photo_url": "https://pic.xiami.net/images/avatar_new/940/47012091_1423224072.jpg@1e_1c_0i_1o_100Q_100w_100h"
          },
          "time": "2015-08-16 09:32",
          "ageree_num": 0,
          "disageree_num": 0,
          "brief": "你可以去看看这张专辑的背面封面 <br><br><a href=\"//emumo.xiami.com/apps/mobile\" target=\"_blank\">来自iPhone客户端</a>",
          "replies": []
        },
        {
          "author": {
            "id": "35210469",
            "name": "虾米用户",
            "motto": "我还没想好要写什么...",
            "link": "https://emumo.xiami.com/u/35210469",
            "photo_url": "https://pic.xiami.net/images/avatar_new/704/5c051ce18238b_35210469_1543838945.jpg@1e_1c_0i_1o_100Q_100w_100h"
          },
          "time": "2015-08-16 09:46",
          "ageree_num": 0,
          "disageree_num": 0,
          "brief": "<q><b>D.R.L说：</b></q>",
          "replies": []
        }
      ]
    },
    {
      "author": {
        "id": "857923",
        "name": "虾米用户",
        "motto": "",
        "link": "https://emumo.xiami.com/u/857923",
        "photo_url": "https://pic.xiami.net/images/avatar_new/17/15/857923/857923_1305135315.jpg@1e_1c_0i_1o_100Q_100w_100h"
      },
      "time": "2014-11-11 22:06",
      "ageree_num": 0,
      "disageree_num": 0,
      "brief": "Mono经典专辑。   @阿婧她有病啊你有药吗",
      "replies": []
    },
    {
      "author": {
        "id": "4863565",
        "name": "虾米用户",
        "motto": "挤出一丝力气",
        "link": "https://emumo.xiami.com/u/4863565",
        "photo_url": "https://pic.xiami.net/images/avatar_new/97/4863565_1396411277.jpg@1e_1c_0i_1o_100Q_100w_100h"
      },
      "time": "2014-10-18 22:59",
      "ageree_num": 0,
      "disageree_num": 0,
      "brief": "唉。。。。。。。",
      "replies": []
    },
    {
      "author": {
        "id": "4478032",
        "name": "虾米用户",
        "motto": "松下千年菊未残",
        "link": "https://emumo.xiami.com/u/4478032",
        "photo_url": "https://pic.xiami.net/images/avatar_new/89/4478032_1487603411.jpg@1e_1c_0i_1o_100Q_100w_100h"
      },
      "time": "2014-10-18 10:51",
      "ageree_num": 0,
      "disageree_num": 0,
      "brief": "这张应该是录音室专辑吧，怎么放在了EP单曲下面",
      "replies": []
    },
    {
      "author": {
        "id": "12232694",
        "name": "虾米用户",
        "motto": "",
        "link": "https://emumo.xiami.com/u/12232694",
        "photo_url": "https://pic.xiami.net/images/avatar_new/244/122326941387984502.jpg@1e_1c_0i_1o_100Q_100w_100h"
      },
      "time": "2014-05-26 19:43",
      "ageree_num": 0,
      "disageree_num": 0,
      "brief": "后摇系列",
      "replies": []
    },
    {
      "author": {
        "id": "5415248",
        "name": "虾米用户",
        "motto": "隐形人",
        "link": "https://emumo.xiami.com/u/5415248",
        "photo_url": "https://pic.xiami.net/images/avatar_new/108/5415248_1387089479.jpg@1e_1c_0i_1o_100Q_100w_100h"
      },
      "time": "2014-05-25 20:31",
      "ageree_num": 0,
      "disageree_num": 0,
      "brief": "后摇",
      "replies": []
    },
    {
      "author": {
        "id": "10982474",
        "name": "虾米用户",
        "motto": "",
        "link": "https://emumo.xiami.com/u/10982474",
        "photo_url": "https://pic.xiami.net/images/avatar/74/10982474/109824741349707001.jpg@1e_1c_0i_1o_100Q_100w_100h"
      },
      "time": "2014-05-23 10:57",
      "ageree_num": 0,
      "disageree_num": 0,
      "brief": "刚刚发现后摇   是我在寻找的。。。",
      "replies": []
    },
    {
      "author": {
        "id": "4298941",
        "name": "虾米用户",
        "motto": " ",
        "link": "https://emumo.xiami.com/u/4298941",
        "photo_url": "https://pic.xiami.net/images/avatar_new/85/5dda60f1e959c_4298941_1574592753.jpg@1e_1c_0i_1o_100Q_100w_100h"
      },
      "time": "2014-05-08 16:42",
      "ageree_num": 0,
      "disageree_num": 0,
      "brief": "MONO这张专我居然没听过╮(╯▽╰)╭",
      "replies": []
    },
    {
      "author": {
        "id": "2653460",
        "name": "虾米用户",
        "motto": "害怕失控，也讨厌被控",
        "link": "https://emumo.xiami.com/u/2653460",
        "photo_url": "https://pic.xiami.net/images/avatar_new/53/6/2653460/2653460_1363094397.jpg@1e_1c_0i_1o_100Q_100w_100h"
      },
      "time": "2013-12-25 00:20",
      "ageree_num": 13,
      "disageree_num": 0,
      "brief": "将来要带进坟墓的",
      "replies": []
    },
    {
      "author": {
        "id": "9549466",
        "name": "虾米用户",
        "motto": "Chopped them...",
        "link": "https://emumo.xiami.com/u/9549466",
        "photo_url": "https://pic.xiami.net/images/avatar/66/9549466/95494661340358616.jpg@1e_1c_0i_1o_100Q_100w_100h"
      },
      "time": "2013-12-24 15:06",
      "ageree_num": 0,
      "disageree_num": 0,
      "brief": "Merry X&amp;#039;mas",
      "replies": []
    },
    {
      "author": {
        "id": "16598686",
        "name": "虾米用户",
        "motto": "。。",
        "link": "https://emumo.xiami.com/u/16598686",
        "photo_url": "https://pic.xiami.net/images/avatar_new/331/16598686_1446456204.jpg@1e_1c_0i_1o_100Q_100w_100h"
      },
      "time": "2013-09-06 21:13",
      "ageree_num": 0,
      "disageree_num": 0,
      "brief": "还是mono听得爽",
      "replies": []
    },
    {
      "author": {
        "id": "16944057",
        "name": "虾米用户",
        "motto": "",
        "link": "https://emumo.xiami.com/u/16944057",
        "photo_url": "https://pic.xiami.net/images/default/xiami_8/avatar_new_3x.png@1e_1c_0i_1o_100Q_100w_100h"
      },
      "time": "2013-07-09 23:21",
      "ageree_num": 0,
      "disageree_num": 0,
      "brief": "nice",
      "replies": []
    },
    {
      "author": {
        "id": "8985729",
        "name": "虾米用户",
        "motto": "",
        "link": "https://emumo.xiami.com/u/8985729",
        "photo_url": "https://pic.xiami.net/images/avatar_new/179/8985729_1420368597.jpg@1e_1c_0i_1o_100Q_100w_100h"
      },
      "time": "2013-04-06 17:55",
      "ageree_num": 0,
      "disageree_num": 0,
      "brief": "后摇",
      "replies": []
    },
    {
      "author": {
        "id": "1377554",
        "name": "虾米用户",
        "motto": "偶尔虚胖无力想养条狗",
        "link": "https://emumo.xiami.com/u/1377554",
        "photo_url": "https://pic.xiami.net/images/avatar_new/27/1377554_1429783797.jpg@1e_1c_0i_1o_100Q_100w_100h"
      },
      "time": "2012-12-29 00:52",
      "ageree_num": 0,
      "disageree_num": 0,
      "brief": "胸闷。第一个听音乐把自己憋死的人。",
      "replies": []
    },
    {
      "author": {
        "id": "8329421",
        "name": "虾米用户",
        "motto": "时光不及你眉眼",
        "link": "https://emumo.xiami.com/u/8329421",
        "photo_url": "https://pic.xiami.net/images/avatar_new/166/5b04c832decee_8329421_1527040050.jpg@1e_1c_0i_1o_100Q_100w_100h"
      },
      "time": "2012-12-28 17:46",
      "ageree_num": 0,
      "disageree_num": 0,
      "brief": "1",
      "replies": []
    },
    {
      "author": {
        "id": "12119945",
        "name": "虾米用户",
        "motto": "sammicc",
        "link": "https://emumo.xiami.com/u/12119945",
        "photo_url": "https://pic.xiami.net/images/avatar_new/242/39/12119945/12119945_1356579766.jpg@1e_1c_0i_1o_100Q_100w_100h"
      },
      "time": "2012-12-27 11:58",
      "ageree_num": 1,
      "disageree_num": 0,
      "brief": "元老级后摇团，没赶上今年夏天的live。但是阴雨天能一直循环播放，然后静下来看看书想想自己，天马行空。",
      "replies": []
    },
    {
      "author": {
        "id": "155947",
        "name": "虾米用户",
        "motto": "一期一会",
        "link": "https://emumo.xiami.com/u/155947",
        "photo_url": "https://pic.xiami.net/images/avatar_new/3/155947_1390804649.jpg@1e_1c_0i_1o_100Q_100w_100h"
      },
      "time": "2012-12-22 05:03",
      "ageree_num": 0,
      "disageree_num": 0,
      "brief": "Hi , R U there ?",
      "replies": []
    },
    {
      "author": {
        "id": "8640457",
        "name": "虾米用户",
        "motto": "分手不要把锅拿走",
        "link": "https://emumo.xiami.com/u/8640457",
        "photo_url": "https://pic.xiami.net/images/avatar_new/172/8640457_1429049591.gif@1e_1c_0i_1o_100Q_100w_100h"
      },
      "time": "2012-11-12 20:38",
      "ageree_num": 0,
      "disageree_num": 0,
      "brief": "走在路上时常听的集。",
      "replies": []
    },
    {
      "author": {
        "id": "5412521",
        "name": "虾米用户",
        "motto": "然而 噩梦已经醒来 美梦",
        "link": "https://emumo.xiami.com/u/5412521",
        "photo_url": "https://pic.xiami.net/images/avatar_new/108/5412521_1449222357.jpg@1e_1c_0i_1o_100Q_100w_100h"
      },
      "time": "2012-09-18 07:48",
      "ageree_num": 0,
      "disageree_num": 0,
      "brief": "918大清早 超儿要走 我突然听到这个 我想你 我操",
      "replies": []
    },
    {
      "author": {
        "id": "7007254",
        "name": "虾米用户",
        "motto": "你要的我都有啊~~",
        "link": "https://emumo.xiami.com/u/7007254",
        "photo_url": "https://pic.xiami.net/images/avatar_new/140/14/7007254/7007254_1322493722.jpg@1e_1c_0i_1o_100Q_100w_100h"
      },
      "time": "2012-09-15 00:10",
      "ageree_num": 0,
      "disageree_num": 0,
      "brief": "日本人的后摇",
      "replies": []
    },
    {
      "author": {
        "id": "1311448",
        "name": "虾米用户",
        "motto": " ",
        "link": "https://emumo.xiami.com/u/1311448",
        "photo_url": "https://pic.xiami.net/images/avatar_new/26/1311448_1404055807.jpg@1e_1c_0i_1o_100Q_100w_100h"
      },
      "time": "2012-08-26 11:25",
      "ageree_num": 0,
      "disageree_num": 0,
      "brief": "i am  here, are you there?",
      "replies": []
    },
    {
      "author": {
        "id": "2752757",
        "name": "虾米用户",
        "motto": "",
        "link": "https://emumo.xiami.com/u/2752757",
        "photo_url": "https://pic.xiami.net/images/avatar_new/55/5/2752757/2752757_1306205647.jpg@1e_1c_0i_1o_100Q_100w_100h"
      },
      "time": "2012-08-20 18:20",
      "ageree_num": 1,
      "disageree_num": 0,
      "brief": "为什么听得全身会有酥麻的赶脚……",
      "replies": []
    },
    {
      "author": {
        "id": "2743530",
        "name": "虾米用户",
        "motto": "",
        "link": "https://emumo.xiami.com/u/2743530",
        "photo_url": "https://pic.xiami.net/images/avatar_new/54/87/2743530/2743530_1306202885.png@1e_1c_0i_1o_100Q_100w_100h"
      },
      "time": "2012-08-05 20:52",
      "ageree_num": 0,
      "disageree_num": 0,
      "brief": "来自心灵的呐喊",
      "replies": []
    },
    {
      "author": {
        "id": "7319541",
        "name": "虾米用户",
        "motto": "",
        "link": "https://emumo.xiami.com/u/7319541",
        "photo_url": "https://pic.xiami.net/images/avatar_new/146/39/7319541/7319541_1337136345.png@1e_1c_0i_1o_100Q_100w_100h"
      },
      "time": "2012-07-31 12:19",
      "ageree_num": 0,
      "disageree_num": 0,
      "brief": "cover",
      "replies": []
    },
    {
      "author": {
        "id": "516791",
        "name": "虾米用户",
        "motto": "假酒喝多了",
        "link": "https://emumo.xiami.com/u/516791",
        "photo_url": "https://pic.xiami.net/images/avatar_new/10/580f29e8318a6_516791_1477388776.jpg@1e_1c_0i_1o_100Q_100w_100h"
      },
      "time": "2012-07-28 16:46",
      "ageree_num": 0,
      "disageree_num": 0,
      "brief": "mono",
      "replies": []
    },
    {
      "author": {
        "id": "1354859",
        "name": "虾米用户",
        "motto": "",
        "link": "https://emumo.xiami.com/u/1354859",
        "photo_url": "https://pic.xiami.net/images/avatar_new/27/9/1354859/1354859_1305273667.jpg@1e_1c_0i_1o_100Q_100w_100h"
      },
      "time": "2012-07-27 14:43",
      "ageree_num": 0,
      "disageree_num": 0,
      "brief": "好封面！好音乐",
      "replies": []
    },
    {
      "author": {
        "id": "2724706",
        "name": "虾米用户",
        "motto": "",
        "link": "https://emumo.xiami.com/u/2724706",
        "photo_url": "https://pic.xiami.net/images/avatar_new/54/49/2724706/2724706_1306197241.jpg@1e_1c_0i_1o_100Q_100w_100h"
      },
      "time": "2012-07-25 17:18",
      "ageree_num": 0,
      "disageree_num": 0,
      "brief": "好，high",
      "replies": []
    },
    {
      "author": {
        "id": "11004",
        "name": "虾米用户",
        "motto": "这家伙很聪明什么也没留下...",
        "link": "https://emumo.xiami.com/u/11004",
        "photo_url": "https://pic.xiami.net/images/artistlogo/60/15155859186460.jpg@1e_1c_0i_1o_100Q_100w_100h"
      },
      "time": "2012-07-17 20:15",
      "ageree_num": 0,
      "disageree_num": 0,
      "brief": "xia zai <a href=\"http://jidangang.com/post/197\" target=\"_blank\" rel=\"nofollow noreferrer noopener\">http://jidangang.com/post/197</a>",
      "replies": []
    },
    {
      "author": {
        "id": "3630121",
        "name": "虾米用户",
        "motto": "",
        "link": "https://emumo.xiami.com/u/3630121",
        "photo_url": "https://pic.xiami.net/images/avatar_new/72/60/3630121/3630121_1306469584.jpg@1e_1c_0i_1o_100Q_100w_100h"
      },
      "time": "2012-07-14 21:59",
      "ageree_num": 0,
      "disageree_num": 0,
      "brief": "yearning相当有魄力~",
      "replies": []
    },
    {
      "author": {
        "id": "2804922",
        "name": "虾米用户",
        "motto": "",
        "link": "https://emumo.xiami.com/u/2804922",
        "photo_url": "https://pic.xiami.net/images/common/uploadpic/54/14840462545562.png@1e_1c_0i_1o_100Q_100w_100h"
      },
      "time": "2012-07-02 18:18",
      "ageree_num": 0,
      "disageree_num": 0,
      "brief": "最后一首最后一首!!",
      "replies": []
    },
    {
      "author": {
        "id": "1683349",
        "name": "虾米用户",
        "motto": "我还没想好要写什么...",
        "link": "https://emumo.xiami.com/u/1683349",
        "photo_url": "https://pic.xiami.net/images/default/xiami_8/avatar_new_3x.png@1e_1c_0i_1o_100Q_100w_100h"
      },
      "time": "2012-06-27 23:27",
      "ageree_num": 0,
      "disageree_num": 0,
      "brief": "这张专辑还是挺有用的",
      "replies": []
    },
    {
      "author": {
        "id": "450722",
        "name": "虾米用户",
        "motto": "中年人徐二千",
        "link": "https://emumo.xiami.com/u/450722",
        "photo_url": "https://pic.xiami.net/images/user/450722/622b33dee6d6496e99e4e04f985fb1ed_a1de39db1c2d4033a31ef17334d13fae.jpg@1e_1c_0i_1o_100Q_100w_100h"
      },
      "time": "2012-05-30 21:52",
      "ageree_num": 0,
      "disageree_num": 0,
      "brief": "you are there",
      "replies": []
    },
    {
      "author": {
        "id": "7943860",
        "name": "虾米用户",
        "motto": "",
        "link": "https://emumo.xiami.com/u/7943860",
        "photo_url": "https://pic.xiami.net/images/avatar_new/158/87/7943860/7943860_1329012549.jpg@1e_1c_0i_1o_100Q_100w_100h"
      },
      "time": "2012-03-28 22:29",
      "ageree_num": 0,
      "disageree_num": 0,
      "brief": "like!",
      "replies": []
    },
    {
      "author": {
        "id": "5739135",
        "name": "虾米用户",
        "motto": "",
        "link": "https://emumo.xiami.com/u/5739135",
        "photo_url": "https://pic.xiami.net/images/avatar_new/114/78/5739135/5739135_1315387731.jpg@1e_1c_0i_1o_100Q_100w_100h"
      },
      "time": "2012-03-16 13:51",
      "ageree_num": 0,
      "disageree_num": 0,
      "brief": "so so",
      "replies": []
    },
    {
      "author": {
        "id": "8432155",
        "name": "虾米用户",
        "motto": "",
        "link": "https://emumo.xiami.com/u/8432155",
        "photo_url": "https://pic.xiami.net/images/avatar_new/168/64/8432155/8432155_1345788034.jpg@1e_1c_0i_1o_100Q_100w_100h"
      },
      "time": "2012-03-15 01:51",
      "ageree_num": 0,
      "disageree_num": 0,
      "brief": "are you there?",
      "replies": []
    },
    {
      "author": {
        "id": "6007647",
        "name": "虾米用户",
        "motto": "",
        "link": "https://emumo.xiami.com/u/6007647",
        "photo_url": "https://pic.xiami.net/images/avatar_new/120/6007647_1403100116.jpg@1e_1c_0i_1o_100Q_100w_100h"
      },
      "time": "2012-03-11 21:51",
      "ageree_num": 0,
      "disageree_num": 0,
      "brief": "u r here~ 梦想与现实 懵懂迷失崩溃不成军 这就是我所理解后摇的魅力！",
      "replies": []
    },
    {
      "author": {
        "id": "563576",
        "name": "虾米用户",
        "motto": "",
        "link": "https://emumo.xiami.com/u/563576",
        "photo_url": "https://pic.xiami.net/images/default/xiami_8/avatar_new_3x.png@1e_1c_0i_1o_100Q_100w_100h"
      },
      "time": "2012-03-03 20:03",
      "ageree_num": 0,
      "disageree_num": 0,
      "brief": "You Are There",
      "replies": []
    },
    {
      "author": {
        "id": "3969170",
        "name": "虾米用户",
        "motto": "",
        "link": "https://emumo.xiami.com/u/3969170",
        "photo_url": "https://pic.xiami.net/images/default/xiami_8/avatar_new_3x.png@1e_1c_0i_1o_100Q_100w_100h"
      },
      "time": "2012-03-03 12:16",
      "ageree_num": 0,
      "disageree_num": 0,
      "brief": "you are here",
      "replies": []
    },
    {
      "author": {
        "id": "7111610",
        "name": "虾米用户",
        "motto": "",
        "link": "https://emumo.xiami.com/u/7111610",
        "photo_url": "https://pic.xiami.net/images/avatar_new/142/23/7111610/7111610_1327416757.jpg@1e_1c_0i_1o_100Q_100w_100h"
      },
      "time": "2012-02-05 17:54",
      "ageree_num": 0,
      "disageree_num": 0,
      "brief": "大气恢宏",
      "replies": []
    },
    {
      "author": {
        "id": "7420735",
        "name": "虾米用户",
        "motto": "",
        "link": "https://emumo.xiami.com/u/7420735",
        "photo_url": "https://pic.xiami.net/images/avatar_new/148/41/7420735/7420735_1324954046.jpg@1e_1c_0i_1o_100Q_100w_100h"
      },
      "time": "2012-02-01 11:21",
      "ageree_num": 0,
      "disageree_num": 0,
      "brief": "我不是很懂，但是听他们的歌，感觉场面很恢宏、大气！与心灵的某处能产生共鸣！",
      "replies": []
    },
    {
      "author": {
        "id": "2269005",
        "name": "虾米用户",
        "motto": "keep balance",
        "link": "https://emumo.xiami.com/u/2269005",
        "photo_url": "https://pic.xiami.net/images/avatar_new/45/2269005_1402593445.png@1e_1c_0i_1o_100Q_100w_100h"
      },
      "time": "2012-01-18 17:52",
      "ageree_num": 0,
      "disageree_num": 0,
      "brief": "听了很多遍，最爱第一首",
      "replies": []
    },
    {
      "author": {
        "id": "3474198",
        "name": "虾米用户",
        "motto": "我还没想好要写什么...",
        "link": "https://emumo.xiami.com/u/3474198",
        "photo_url": "https://pic.xiami.net/images/avatar_new/69/5abb74e92e90f_3474198_1522234601.jpg@1e_1c_0i_1o_100Q_100w_100h"
      },
      "time": "2011-12-26 00:55",
      "ageree_num": 0,
      "disageree_num": 0,
      "brief": "i wish,too",
      "replies": []
    },
    {
      "author": {
        "id": "2724706",
        "name": "虾米用户",
        "motto": "",
        "link": "https://emumo.xiami.com/u/2724706",
        "photo_url": "https://pic.xiami.net/images/avatar_new/54/49/2724706/2724706_1306197241.jpg@1e_1c_0i_1o_100Q_100w_100h"
      },
      "time": "2011-12-15 13:38",
      "ageree_num": 0,
      "disageree_num": 0,
      "brief": "h",
      "replies": []
    },
    {
      "author": {
        "id": "2005458",
        "name": "虾米用户",
        "motto": "",
        "link": "https://emumo.xiami.com/u/2005458",
        "photo_url": "https://pic.xiami.net/images/avatar_new/40/10/2005458/2005458_1327144005.jpg@1e_1c_0i_1o_100Q_100w_100h"
      },
      "time": "2011-12-07 23:29",
      "ageree_num": 0,
      "disageree_num": 0,
      "brief": "带上耳机，听MONO的这个专辑，细腻，温暖。",
      "replies": []
    },
    {
      "author": {
        "id": "18205",
        "name": "虾米用户",
        "motto": "我还没想好要写什么...",
        "link": "https://emumo.xiami.com/u/18205",
        "photo_url": "https://pic.xiami.net/images/avatar_new/0/5a2b96a0cb728_18205_1512806048.jpg@1e_1c_0i_1o_100Q_100w_100h"
      },
      "time": "2011-12-06 12:16",
      "ageree_num": 0,
      "disageree_num": 0,
      "brief": "这张无法解释的，可惜被同学删了",
      "replies": []
    },
    {
      "author": {
        "id": "633789",
        "name": "虾米用户",
        "motto": "我还没想好要写什么...",
        "link": "https://emumo.xiami.com/u/633789",
        "photo_url": "https://pic.xiami.net/images/avatar_new/12/633789_1564734567.jpg@1e_1c_0i_1o_100Q_100w_100h"
      },
      "time": "2011-12-04 16:37",
      "ageree_num": 0,
      "disageree_num": 0,
      "brief": "mono dont fear satan",
      "replies": []
    },
    {
      "author": {
        "id": "7030889",
        "name": "虾米用户",
        "motto": "",
        "link": "https://emumo.xiami.com/u/7030889",
        "photo_url": "https://pic.xiami.net/images/avatar_new/140/61/7030889/7030889_1322628471.jpg@1e_1c_0i_1o_100Q_100w_100h"
      },
      "time": "2011-12-03 23:16",
      "ageree_num": 0,
      "disageree_num": 0,
      "brief": "哼喜欢",
      "replies": []
    },
    {
      "author": {
        "id": "3382779",
        "name": "虾米用户",
        "motto": "",
        "link": "https://emumo.xiami.com/u/3382779",
        "photo_url": "https://pic.xiami.net/images/avatar_new/67/65/3382779/3382779_1310460426.jpg@1e_1c_0i_1o_100Q_100w_100h"
      },
      "time": "2011-11-11 17:18",
      "ageree_num": 0,
      "disageree_num": 0,
      "brief": "很用心～",
      "replies": []
    },
    {
      "author": {
        "id": "2888650",
        "name": "虾米用户",
        "motto": "Wonky Jazz",
        "link": "https://emumo.xiami.com/u/2888650",
        "photo_url": "https://pic.xiami.net/images/avatar_new/57/2888650_1422122194.jpg@1e_1c_0i_1o_100Q_100w_100h"
      },
      "time": "2011-08-16 17:53",
      "ageree_num": 0,
      "disageree_num": 0,
      "brief": "X",
      "replies": []
    },
    {
      "author": {
        "id": "4313652",
        "name": "虾米用户",
        "motto": "一念起，萬水千山",
        "link": "https://emumo.xiami.com/u/4313652",
        "photo_url": "https://pic.xiami.net/images/avatar_new/86/27/4313652/4313652_1308372140.jpg@1e_1c_0i_1o_100Q_100w_100h"
      },
      "time": "2011-08-03 08:01",
      "ageree_num": 0,
      "disageree_num": 0,
      "brief": "像在触摸一个分不清真假的梦",
      "replies": []
    },
    {
      "author": {
        "id": "2064090",
        "name": "虾米用户",
        "motto": "",
        "link": "https://emumo.xiami.com/u/2064090",
        "photo_url": "https://pic.xiami.net/images/default/xiami_8/avatar_new_3x.png@1e_1c_0i_1o_100Q_100w_100h"
      },
      "time": "2011-07-25 23:31",
      "ageree_num": 0,
      "disageree_num": 0,
      "brief": "酷",
      "replies": []
    },
    {
      "author": {
        "id": "451434",
        "name": "虾米用户",
        "motto": "",
        "link": "https://emumo.xiami.com/u/451434",
        "photo_url": "https://pic.xiami.net/images/avatar_new/9/2/451434/451434_1305066905.jpg@1e_1c_0i_1o_100Q_100w_100h"
      },
      "time": "2011-07-04 05:01",
      "ageree_num": 0,
      "disageree_num": 0,
      "brief": "居然要15胖子，便宜点好不。。。",
      "replies": []
    },
    {
      "author": {
        "id": "3345419",
        "name": "虾米用户",
        "motto": "SADNESS",
        "link": "https://emumo.xiami.com/u/3345419",
        "photo_url": "https://pic.xiami.net/images/avatar_new/66/3345419_1510053236.jpg@1e_1c_0i_1o_100Q_100w_100h"
      },
      "time": "2011-06-14 21:35",
      "ageree_num": 0,
      "disageree_num": 0,
      "brief": "mono的You Are There 这张我认为是最棒的一张，沁人心脾  post-rock中的极品",
      "replies": []
    },
    {
      "author": {
        "id": "2782344",
        "name": "虾米用户",
        "motto": "我还没想好要写什么...",
        "link": "https://emumo.xiami.com/u/2782344",
        "photo_url": "https://pic.xiami.net/images/avatar_new/55/64/2782344/2782344_1337954543.jpg@1e_1c_0i_1o_100Q_100w_100h"
      },
      "time": "2011-05-29 11:29",
      "ageree_num": 0,
      "disageree_num": 0,
      "brief": "最爱",
      "replies": []
    },
    {
      "author": {
        "id": "563576",
        "name": "虾米用户",
        "motto": "",
        "link": "https://emumo.xiami.com/u/563576",
        "photo_url": "https://pic.xiami.net/images/default/xiami_8/avatar_new_3x.png@1e_1c_0i_1o_100Q_100w_100h"
      },
      "time": "2011-05-17 00:21",
      "ageree_num": 0,
      "disageree_num": 0,
      "brief": "恩 这张真的是mono最神奇的一张专辑。。Yearning、 Are you there都美死了，尤其Yearning！安静然后突然躁动，总能惊吓，但是很快又会安静。。不过还是最爱更早前得Lost snow，有机会能在现场听到就好了",
      "replies": []
    },
    {
      "author": {
        "id": "3359908",
        "name": "虾米用户",
        "motto": "",
        "link": "https://emumo.xiami.com/u/3359908",
        "photo_url": "https://pic.xiami.net/images/avatar_new/67/19/3359908/33599081379170459.jpg@1e_1c_0i_1o_100Q_100w_100h"
      },
      "time": "2011-05-03 15:17",
      "ageree_num": 0,
      "disageree_num": 0,
      "brief": "超有意境的一张专辑",
      "replies": []
    },
    {
      "author": {
        "id": "3489791",
        "name": "虾米用户",
        "motto": "…",
        "link": "https://emumo.xiami.com/u/3489791",
        "photo_url": "https://pic.xiami.net/images/avatar_new/69/57381792d09e5_3489791_1463293842.jpg@1e_1c_0i_1o_100Q_100w_100h"
      },
      "time": "2011-04-17 02:35",
      "ageree_num": 1,
      "disageree_num": 0,
      "brief": "mono在我心目中的第一专辑。<br>第二 one step more and you die",
      "replies": []
    },
    {
      "author": {
        "id": "3291713",
        "name": "虾米用户",
        "motto": "",
        "link": "https://emumo.xiami.com/u/3291713",
        "photo_url": "https://pic.xiami.net/images/default/xiami_8/avatar_new_3x.png@1e_1c_0i_1o_100Q_100w_100h"
      },
      "time": "2011-03-22 21:51",
      "ageree_num": 0,
      "disageree_num": 0,
      "brief": "总能让你想起很多事",
      "replies": []
    },
    {
      "author": {
        "id": "745486",
        "name": "虾米用户",
        "motto": "变色龙是什么颜色？",
        "link": "https://emumo.xiami.com/u/745486",
        "photo_url": "https://pic.xiami.net/images/avatar_new/14/90/745486/745486_1305117733.jpg@1e_1c_0i_1o_100Q_100w_100h"
      },
      "time": "2011-01-22 17:21",
      "ageree_num": 0,
      "disageree_num": 0,
      "brief": "又是因为砖封~",
      "replies": []
    },
    {
      "author": {
        "id": "1675491",
        "name": "虾米用户",
        "motto": "",
        "link": "https://emumo.xiami.com/u/1675491",
        "photo_url": "https://pic.xiami.net/images/avatar_new/33/50/1675491/1675491_1305882312.jpg@1e_1c_0i_1o_100Q_100w_100h"
      },
      "time": "2010-12-18 20:43",
      "ageree_num": 0,
      "disageree_num": 0,
      "brief": "这专辑都没多少人听吗？",
      "replies": []
    }
  ]
}