{
  "id": "111560209",
  "link": "https://emumo.xiami.com/album/111560209",
  "name": "Fusion",
  "photo_url": "https://pic.xiami.net/images/album/img90/1011554990/1115602091459842562.jpg@4e_1c_100Q_185w_185h",
  "artist_name": "过又嘉",
  "languages": [
    "国语"
  ],
  "companies": [
    "独立发行"
  ],
  "published_date": [
    "2014年09月24日"
  ],
  "categories": [
    "EP",
    "单曲"
  ],
  "styles": [
    "世界融合 World Fusion",
    "沙发音乐 Lounge"
  ],
  "play_count_num": 181571,
  "favorite_count_num": 139,
  "comments_num": 23,
  "intro": "<p><span class=\"s1\">Chinese lounge </span>是我想了很久觉得最为合适这张<span class=\"s1\">EP</span>的形容词，与国内现主流音乐不同，听起来<span class=\"s1\">  </span>养心<span class=\"s1\"> </span>惬意<span class=\"s1\"> </span>又有一丝对各种元素的神秘感！过又嘉<span class=\"s1\">EP</span>名《<span class=\"s1\">Fusion</span>》所有词，曲，制作，演唱均由这位才女一人完成。<br>\n<span class=\"s1\"><br>\nEP</span>名《<span class=\"s1\">Fusion</span>》<span class=\"s1\"> </span>译为融合，也许你听过<span class=\"s1\"> Fusion jazz</span>、<span class=\"s1\"> Fusion rock</span>，等等多种融合的音乐，但现在我们听到的是一种全新的带有东方韵味的融合，它不同于传统的流行音乐，在这张<span class=\"s1\">EP</span>里你可以听到一些宗教的色彩，一些禅意，马头琴、甚至还有一些京剧的口述唱段等诸多元素，翻看歌词，<span class=\"s1\"> </span>道家文化和古诗词都在其中<span class=\"s1\"> </span>正是这些看似不可能融合的元素、才有种能快速把你抽离现实的魔力，让你安静的度过几分钟，去思考，去回味。 </p>",
  "songs": [
    {
      "name": "序曲",
      "link": "https://emumo.xiami.com/song/xL7FIAd9cc7"
    },
    {
      "name": "禅道",
      "link": "https://emumo.xiami.com/song/bqvu9N536b23"
    },
    {
      "name": "春雪",
      "link": "https://emumo.xiami.com/song/xL7FIC99975"
    },
    {
      "name": "梦",
      "link": "https://emumo.xiami.com/song/xL7FID9e481"
    }
  ],
  "comments": [
    {
      "author": {
        "id": "55011784",
        "name": "虾米用户",
        "motto": "喜欢民谣，无条件的喜欢",
        "link": "https://emumo.xiami.com/u/55011784",
        "photo_url": "https://pic.xiami.net/images/user/55011784/d39e6a59e52e438a994dc510d229a4ba_cf79a4d0d54d4a1c9d30399b8864965c.jpg@1e_1c_0i_1o_100Q_100w_100h"
      },
      "time": "2019-03-10 21:35",
      "ageree_num": 0,
      "disageree_num": 0,
      "brief": "太喜欢了，希望过又嘉能火起来",
      "replies": []
    },
    {
      "author": {
        "id": "30800139",
        "name": "虾米用户",
        "motto": "我在低俗与高雅间活的很尴...",
        "link": "https://emumo.xiami.com/u/30800139",
        "photo_url": "https://pic.xiami.net/images/avatar_new/616/308001391388402667.jpg@1e_1c_0i_1o_100Q_100w_100h"
      },
      "time": "2018-03-06 05:31",
      "ageree_num": 0,
      "disageree_num": 0,
      "brief": "。                     <br><br><a href=\"//emumo.xiami.com/apps/mobile\" target=\"_blank\">来自iPhone客户端</a>",
      "replies": []
    },
    {
      "author": {
        "id": "17005106",
        "name": "虾米用户",
        "motto": "吸引容易，互相吸引难",
        "link": "https://emumo.xiami.com/u/17005106",
        "photo_url": "https://pic.xiami.net/images/avatar_new/340/57fda80def43b_17005106_1476241421.jpg@1e_1c_0i_1o_100Q_100w_100h"
      },
      "time": "2018-01-18 09:50",
      "ageree_num": 0,
      "disageree_num": 0,
      "brief": "很赞！居然才发现！！                     <br><br><a href=\"//emumo.xiami.com/apps/mobile\" target=\"_blank\">来自iPhone客户端</a>",
      "replies": []
    },
    {
      "author": {
        "id": "19307833",
        "name": "虾米用户",
        "motto": "音乐像巧克力么",
        "link": "https://emumo.xiami.com/u/19307833",
        "photo_url": "https://pic.xiami.net/images/avatar_new/386/5e756aa0f0502_19307833_1584753312.jpg@1e_1c_0i_1o_100Q_100w_100h"
      },
      "time": "2016-09-10 18:38",
      "ageree_num": 0,
      "disageree_num": 0,
      "brief": "魔性 魔力 的 声音 音乐",
      "replies": []
    },
    {
      "author": {
        "id": "2591642",
        "name": "虾米用户",
        "motto": "空有长河",
        "link": "https://emumo.xiami.com/u/2591642",
        "photo_url": "https://pic.xiami.net/images/user/2591642/5abcf60f551348a4875dc985477caf5b_0615aa7b43a24acfad4897f24dc5b262.jpg@1e_1c_0i_1o_100Q_100w_100h"
      },
      "time": "2016-08-31 03:54",
      "ageree_num": 0,
      "disageree_num": 0,
      "brief": "还是喜欢原来的封面…                     <br><br><a href=\"//emumo.xiami.com/apps/mobile\" target=\"_blank\">来自iPhone客户端</a>",
      "replies": []
    },
    {
      "author": {
        "id": "14848226",
        "name": "虾米用户",
        "motto": "我还没想好要写什么...",
        "link": "https://emumo.xiami.com/u/14848226",
        "photo_url": "https://pic.xiami.net/images/avatar_new/296/5e8f371c618c3_14848226_1586444060.jpg@1e_1c_0i_1o_100Q_100w_100h"
      },
      "time": "2016-04-06 15:13",
      "ageree_num": 0,
      "disageree_num": 0,
      "brief": "人美声甜~很不错~！",
      "replies": []
    },
    {
      "author": {
        "id": "52641981",
        "name": "虾米用户",
        "motto": "",
        "link": "https://emumo.xiami.com/u/52641981",
        "photo_url": "https://pic.xiami.net/images/default/xiami_8/avatar_new_3x.png@1e_1c_0i_1o_100Q_100w_100h"
      },
      "time": "2016-04-06 15:10",
      "ageree_num": 0,
      "disageree_num": 0,
      "brief": "很棒的一张专辑！",
      "replies": []
    },
    {
      "author": {
        "id": "22767680",
        "name": "虾米用户",
        "motto": "擎一枝青伞，随花飞到天尽...",
        "link": "https://emumo.xiami.com/u/22767680",
        "photo_url": "https://pic.xiami.net/images/avatar_new/455/5c34333e3c583_22767680_1546924862.jpg@1e_1c_0i_1o_100Q_100w_100h"
      },
      "time": "2015-04-11 23:36",
      "ageree_num": 0,
      "disageree_num": 0,
      "brief": "只觉得春雪好听                     <br><br><a href=\"//emumo.xiami.com/apps/mobile\" target=\"_blank\">来自iPhone客户端</a>",
      "replies": []
    },
    {
      "author": {
        "id": "13073595",
        "name": "虾米用户",
        "motto": "",
        "link": "https://emumo.xiami.com/u/13073595",
        "photo_url": "https://pic.xiami.net/images/default/xiami_8/avatar_new_3x.png@1e_1c_0i_1o_100Q_100w_100h"
      },
      "time": "2015-01-27 10:49",
      "ageree_num": 0,
      "disageree_num": 0,
      "brief": "不错",
      "replies": []
    },
    {
      "author": {
        "id": "3067058",
        "name": "虾米用户",
        "motto": "",
        "link": "https://emumo.xiami.com/u/3067058",
        "photo_url": "https://pic.xiami.net/images/avatar_new/61/34/3067058/3067058_1306300148.jpg@1e_1c_0i_1o_100Q_100w_100h"
      },
      "time": "2015-01-26 22:26",
      "ageree_num": 0,
      "disageree_num": 0,
      "brief": "刚听觉得特别 再听其实容易被淹没。<br> 《梦》听了三遍 不知为啥有一种一直在听带和声的伴奏的感觉 ，大概是被伴奏的节奏抢了戏。",
      "replies": []
    },
    {
      "author": {
        "id": "9883974",
        "name": "虾米用户",
        "motto": "jazz fun",
        "link": "https://emumo.xiami.com/u/9883974",
        "photo_url": "https://pic.xiami.net/images/avatar_new/197/9883974_1414929804.jpg@1e_1c_0i_1o_100Q_100w_100h"
      },
      "time": "2014-11-07 21:14",
      "ageree_num": 0,
      "disageree_num": 0,
      "brief": "感觉比较特别，难得听到的原创音乐",
      "replies": []
    },
    {
      "author": {
        "id": "6850030",
        "name": "虾米用户",
        "motto": "笑而不语的思前想后@@",
        "link": "https://emumo.xiami.com/u/6850030",
        "photo_url": "https://pic.xiami.net/images/avatar_new/137/0/6850030/6850030_1321631168.jpg@1e_1c_0i_1o_100Q_100w_100h"
      },
      "time": "2014-10-30 09:08",
      "ageree_num": 0,
      "disageree_num": 0,
      "brief": "文艺十足 <br><br><a href=\"//emumo.xiami.com/apps/mobile\" target=\"_blank\">来自android客户端</a>",
      "replies": []
    },
    {
      "author": {
        "id": "8412567",
        "name": "虾米用户",
        "motto": "",
        "link": "https://emumo.xiami.com/u/8412567",
        "photo_url": "https://pic.xiami.net/images/avatar/67/8412567/84125671331609050.jpg@1e_1c_0i_1o_100Q_100w_100h"
      },
      "time": "2014-10-27 21:54",
      "ageree_num": 0,
      "disageree_num": 0,
      "brief": "虾米把这个归类为世界音乐风格，个人感觉有点牵强，不过，味道还是不错的。",
      "replies": [
        {
          "author": {
            "id": "5635",
            "name": "虾米用户",
            "motto": "",
            "link": "https://emumo.xiami.com/u/5635",
            "photo_url": "https://pic.xiami.net/images/avatar_new/0/11/5635/5635_1304932684.jpg@1e_1c_0i_1o_100Q_100w_100h"
          },
          "time": "2014-11-16 04:31",
          "ageree_num": 0,
          "disageree_num": 0,
          "brief": "个人定义，这是音乐人 <br><br><a href=\"//emumo.xiami.com/apps/mobile\" target=\"_blank\">来自iPhone客户端</a>",
          "replies": []
        }
      ]
    },
    {
      "author": {
        "id": "5470230",
        "name": "虾米用户",
        "motto": "",
        "link": "https://emumo.xiami.com/u/5470230",
        "photo_url": "https://pic.xiami.net/images/avatar_new/109/40/5470230/5470230_1315279192.jpg@1e_1c_0i_1o_100Q_100w_100h"
      },
      "time": "2014-10-23 06:58",
      "ageree_num": 0,
      "disageree_num": 0,
      "brief": "嗓音太刻意了。",
      "replies": []
    },
    {
      "author": {
        "id": "5176645",
        "name": "虾米用户",
        "motto": "Seek inner p...",
        "link": "https://emumo.xiami.com/u/5176645",
        "photo_url": "https://pic.xiami.net/images/avatar_new/103/53/5176645/5176645_1312738359.jpg@1e_1c_0i_1o_100Q_100w_100h"
      },
      "time": "2014-10-20 11:11",
      "ageree_num": 0,
      "disageree_num": 0,
      "brief": "好听！迷幻的中国风~",
      "replies": []
    },
    {
      "author": {
        "id": "369150",
        "name": "虾米用户",
        "motto": "♥︎stay hunge...",
        "link": "https://emumo.xiami.com/u/369150",
        "photo_url": "https://pic.xiami.net/images/user/369150/6eaab8f534ae425bb6eaf23865a40b34_baedb5c5e0fd45aaabd7d3e4b1837649.jpg@1e_1c_0i_1o_100Q_100w_100h"
      },
      "time": "2014-10-19 23:58",
      "ageree_num": 0,
      "disageree_num": 0,
      "brief": "的确不错 <br><br><a href=\"//emumo.xiami.com/apps/mobile\" target=\"_blank\">来自iPhone客户端</a>",
      "replies": []
    },
    {
      "author": {
        "id": "5953370",
        "name": "虾米用户",
        "motto": "很懒，什么都没干",
        "link": "https://emumo.xiami.com/u/5953370",
        "photo_url": "https://pic.xiami.net/images/user/5953370/f93a983d34c2442092a06b5fa2817475_f7c2b3ac0733462a8831962b77c8f6ac.jpg@1e_1c_0i_1o_100Q_100w_100h"
      },
      "time": "2014-10-19 10:08",
      "ageree_num": 0,
      "disageree_num": 0,
      "brief": "好听！这俩字就够了",
      "replies": []
    },
    {
      "author": {
        "id": "13324427",
        "name": "虾米用户",
        "motto": " ",
        "link": "https://emumo.xiami.com/u/13324427",
        "photo_url": "https://pic.xiami.net/images/avatar_new/266/56c8ab8e4672b_13324427_1455991694.jpg@1e_1c_0i_1o_100Q_100w_100h"
      },
      "time": "2014-10-19 04:11",
      "ageree_num": 0,
      "disageree_num": 0,
      "brief": "出名只是时间问题",
      "replies": []
    },
    {
      "author": {
        "id": "1132240",
        "name": "虾米用户",
        "motto": "当时明月在，曾照彩云归",
        "link": "https://emumo.xiami.com/u/1132240",
        "photo_url": "https://pic.xiami.net/images/avatar_new/22/1132240_1405905991.jpg@1e_1c_0i_1o_100Q_100w_100h"
      },
      "time": "2014-10-17 21:43",
      "ageree_num": 0,
      "disageree_num": 0,
      "brief": "挺好听的",
      "replies": []
    },
    {
      "author": {
        "id": "2562218",
        "name": "虾米用户",
        "motto": "",
        "link": "https://emumo.xiami.com/u/2562218",
        "photo_url": "https://pic.xiami.net/images/avatar_new/51/2562218_1409815546.jpg@1e_1c_0i_1o_100Q_100w_100h"
      },
      "time": "2014-10-15 20:16",
      "ageree_num": 0,
      "disageree_num": 0,
      "brief": "很特别，好听！ <br><br><a href=\"//emumo.xiami.com/apps/mobile\" target=\"_blank\">来自android客户端</a>",
      "replies": []
    },
    {
      "author": {
        "id": "23161745",
        "name": "虾米用户",
        "motto": "无情无义，没心没肺",
        "link": "https://emumo.xiami.com/u/23161745",
        "photo_url": "https://pic.xiami.net/images/avatar_new/463/23161745_1409677143.jpg@1e_1c_0i_1o_100Q_100w_100h"
      },
      "time": "2014-10-13 16:41",
      "ageree_num": 0,
      "disageree_num": 0,
      "brief": "不错啊，有人在听嘛 <br><br><a href=\"//emumo.xiami.com/apps/mobile\" target=\"_blank\">来自android客户端</a>",
      "replies": []
    },
    {
      "author": {
        "id": "41813836",
        "name": "虾米用户",
        "motto": " ",
        "link": "https://emumo.xiami.com/u/41813836",
        "photo_url": "https://pic.xiami.net/images/avatar_new/836/56b47da4afd54_41813836_1454669220.jpg@1e_1c_0i_1o_100Q_100w_100h"
      },
      "time": "2014-09-29 00:14",
      "ageree_num": 0,
      "disageree_num": 0,
      "brief": "好听 喜欢！",
      "replies": []
    }
  ]
}