{
  "name": "雷速登闪电冲线",
  "link": "https://emumo.xiami.com/song/mSrF0955323",
  "id": "1795726955",
  "album_name": "贝瓦儿歌 系列12",
  "singers": "贝瓦儿歌",
  "play_count_num": 52914,
  "share_count_num": 105,
  "comments_num": 60,
  "lyric": "Flash 加油<br>\nFlash 加油<br>\n雷速登赛手们 快速加油<br>\n<br>\n在赛道飞驰<br>\n沿途颠簸起伏中摇摆<br>\n多少事情在掌握内<br>\n多少是意料之外<br>\n<br>\n看你追我赶<br>\n<br>\n分秒间比试反应能耐<br>\n战况激烈心愈澎湃<br>\n闪电冲线 热切期待<br>\n<br>\n放眼世界 天大地大<br>\n只要相信梦想就会存在<br>\n胜利大门 等我来打开<br>\n<br>\n来吧 flash 加油<br>\nFlash 加油<br>\n雷速登赛手们 快速加油<br>\n弯弯曲曲 闪电飘移<br>\n冲破重重障碍 超越对手<br>\n每次比赛 技术交流<br>\n坚毅奋斗 一展身手<br>\n为争取胜利 不到最后不罢休<br>\n面对挫败 誓不低头",
  "lyric_extra": "",
  "comments": [
    {
      "author": {
        "id": "428011561",
        "name": "虾米用户",
        "motto": "",
        "link": "https://emumo.xiami.com/u/428011561",
        "photo_url": "https://pic.xiami.net/images/user/428011561/f53c57ca7f69430fad4d6299253dca54_86332902f3694da8931f586fea93a166.jpg@1e_1c_0i_1o_100Q_100w_100h"
      },
      "time": "2020-10-09 17:03",
      "ageree_num": 0,
      "disageree_num": 0,
      "brief": "路过看看                     <br><br><a href=\"//emumo.xiami.com/apps/mobile\" target=\"_blank\">来自android客户端</a>",
      "replies": []
    },
    {
      "author": {
        "id": "444836575",
        "name": "虾米用户",
        "motto": "一只超小的古月娜",
        "link": "https://emumo.xiami.com/u/444836575",
        "photo_url": "https://pic.xiami.net/images/user/444836575/d93bff184ad04693b127d1d6663ba58c_52e38ebeccba40b5925e289bc9c5e9f7.jpg@1e_1c_0i_1o_100Q_100w_100h"
      },
      "time": "2020-09-28 22:47",
      "ageree_num": 0,
      "disageree_num": 0,
      "brief": "小时候听着很燃很帅，现在越听越尬&amp;hellip;&amp;hellip;以前看他们念出什么：闪电漂移，神龙摆尾，无级变速，逆向无级变速，瞬间善意，幻影闪移，飓风展翅，裂空神斩，无幻太极啥的&amp;hellip;&amp;hellip;真的是越看越尬，不知道为什么                     <br><br><a href=\"//emumo.xiami.com/apps/mobile\" target=\"_blank\">来自android客户端</a>",
      "replies": []
    },
    {
      "author": {
        "id": "405301525",
        "name": "虾米用户",
        "motto": "",
        "link": "https://emumo.xiami.com/u/405301525",
        "photo_url": "https://pic.xiami.net/images/default/xiami_8/avatar_new_3x.png@1e_1c_0i_1o_100Q_100w_100h"
      },
      "time": "2019-12-08 19:46",
      "ageree_num": 0,
      "disageree_num": 0,
      "brief": "刀片超车！！ <img src=\"//img.xiami.net/res/js/jquery/editor/sets/bbcode/images/smilies/default/415.png\">                     <br><br><a href=\"//emumo.xiami.com/apps/mobile\" target=\"_blank\">来自android客户端</a>",
      "replies": []
    },
    {
      "author": {
        "id": "431580569",
        "name": "虾米用户",
        "motto": "",
        "link": "https://emumo.xiami.com/u/431580569",
        "photo_url": "https://pic.xiami.net/images/user/431580569/eabe44b6edf34d2b83d52979b377ea89_1a59cc4769384d49baf45119b17107da.jpg@1e_1c_0i_1o_100Q_100w_100h"
      },
      "time": "2019-11-05 22:07",
      "ageree_num": 0,
      "disageree_num": 0,
      "brief": "闪电漂移！                     <br><br><a href=\"//emumo.xiami.com/apps/mobile\" target=\"_blank\">来自android客户端</a>",
      "replies": []
    },
    {
      "author": {
        "id": "190186380",
        "name": "虾米用户",
        "motto": "",
        "link": "https://emumo.xiami.com/u/190186380",
        "photo_url": "https://pic.xiami.net/images/avatar_new/3803/579ae3605ef2c_190186380_1469768544.png@1e_1c_0i_1o_100Q_100w_100h"
      },
      "time": "2019-09-16 23:48",
      "ageree_num": 3,
      "disageree_num": 0,
      "brief": "神龙摆尾 刀片超车！！！！                     <br><br><a href=\"//emumo.xiami.com/apps/mobile\" target=\"_blank\">来自android客户端</a>",
      "replies": []
    },
    {
      "author": {
        "id": "428344607",
        "name": "虾米用户",
        "motto": "爱好收集玩具枪",
        "link": "https://emumo.xiami.com/u/428344607",
        "photo_url": "https://pic.xiami.net/images/user/428344607/c9e6bd6a638f478dbcff2945f932a252_dd982287fef149fbb2c308f8d5215d38.jpg@1e_1c_0i_1o_100Q_100w_100h"
      },
      "time": "2019-08-16 17:11",
      "ageree_num": 1,
      "disageree_num": 0,
      "brief": "好就是太短了                     <br><br><a href=\"//emumo.xiami.com/apps/mobile\" target=\"_blank\">来自android客户端</a>",
      "replies": []
    },
    {
      "author": {
        "id": "187128044",
        "name": "虾米用户",
        "motto": "360º旋转 疯狂跳跃 ...",
        "link": "https://emumo.xiami.com/u/187128044",
        "photo_url": "https://pic.xiami.net/images/user/187128044/8f1b407b1817477dae5dbcca7f287a06_daa6ade838c246eb9eacc8c731723b3c.jpg@1e_1c_0i_1o_100Q_100w_100h"
      },
      "time": "2019-05-23 11:10",
      "ageree_num": 1,
      "disageree_num": 0,
      "brief": "突然想起来了，就过来了                     <br><br><a href=\"//emumo.xiami.com/apps/mobile\" target=\"_blank\">来自android客户端</a>",
      "replies": []
    },
    {
      "author": {
        "id": "414500161",
        "name": "虾米用户",
        "motto": "没得签名",
        "link": "https://emumo.xiami.com/u/414500161",
        "photo_url": "https://pic.xiami.net/images/user/414500161/9521367cb6574d59ad2daad532bfad96_a07c4ec3720e4c1a9c6db08c064dc9bc.jpg@1e_1c_0i_1o_100Q_100w_100h"
      },
      "time": "2019-05-07 08:13",
      "ageree_num": 3,
      "disageree_num": 0,
      "brief": "旋风乱舞 刀片超车  剑鲨巡航 神龙摆尾 雷龙破风 还有最经典的闪电漂移                     <br><br><a href=\"//emumo.xiami.com/apps/mobile\" target=\"_blank\">来自android客户端</a>",
      "replies": []
    },
    {
      "author": {
        "id": "410637045",
        "name": "虾米用户",
        "motto": "中伤不是你的强项，黑夜看...",
        "link": "https://emumo.xiami.com/u/410637045",
        "photo_url": "https://pic.xiami.net/images/avatar_new/8212/5c15c7cd4b405_410637045_b_w108h108.png@1e_1c_0i_1o_100Q_100w_100h"
      },
      "time": "2019-04-06 22:01",
      "ageree_num": 0,
      "disageree_num": 0,
      "brief": "最喜欢第二部，闪电漂移双子旋风哈                     <br><br><a href=\"//emumo.xiami.com/apps/mobile\" target=\"_blank\">来自android客户端</a>",
      "replies": []
    },
    {
      "author": {
        "id": "275663776",
        "name": "虾米用户",
        "motto": "",
        "link": "https://emumo.xiami.com/u/275663776",
        "photo_url": "https://pic.xiami.net/images/avatar_new/800393729_1487864027.jpg@1e_1c_0i_1o_100Q_100w_100h"
      },
      "time": "2019-03-30 18:33",
      "ageree_num": 0,
      "disageree_num": 0,
      "brief": "啊啊啊                     <br><br><a href=\"//emumo.xiami.com/apps/mobile\" target=\"_blank\">来自iPhone客户端</a>",
      "replies": []
    },
    {
      "author": {
        "id": "352828227",
        "name": "虾米用户",
        "motto": "",
        "link": "https://emumo.xiami.com/u/352828227",
        "photo_url": "https://pic.xiami.net/images/user/352828227/f1e82124bac245cb92db6f883125c3cd_a5af7e26daaa4a2b8c465870c99c7565.jpg@1e_1c_0i_1o_100Q_100w_100h"
      },
      "time": "2019-03-15 12:56",
      "ageree_num": 3,
      "disageree_num": 0,
      "brief": "曾经是跟表哥一起看的，之后我们很羡慕里面的凌风凌云两兄弟，我们也买了他们的同款四驱车，现在虽说我们都长大了，但是我们永远是兄嘚！ <img src=\"//img.xiami.net/res/js/jquery/editor/sets/bbcode/images/smilies/default/409.png\"> <br><br><a href=\"//emumo.xiami.com/apps/mobile\" target=\"_blank\">来自android客户端</a>",
      "replies": []
    },
    {
      "author": {
        "id": "356005005",
        "name": "虾米用户",
        "motto": "无个性，不签名",
        "link": "https://emumo.xiami.com/u/356005005",
        "photo_url": "https://pic.xiami.net/images/user/356005005/8a5e281b0d1c485fa7687d475aa184d9_bda869c899fe4c7baabc40c2c4379d3e.jpg@1e_1c_0i_1o_100Q_100w_100h"
      },
      "time": "2019-02-21 20:24",
      "ageree_num": 0,
      "disageree_num": 0,
      "brief": "只有我是90后吧（1999） <br><br><a href=\"//emumo.xiami.com/apps/mobile\" target=\"_blank\">来自android客户端</a>",
      "replies": []
    },
    {
      "author": {
        "id": "28217789",
        "name": "虾米用户",
        "motto": " ",
        "link": "https://emumo.xiami.com/u/28217789",
        "photo_url": "https://pic.xiami.net/images/avatar_new/564/577778e046d4c_28217789_1467447520.jpg@1e_1c_0i_1o_100Q_100w_100h"
      },
      "time": "2019-02-10 21:47",
      "ageree_num": 0,
      "disageree_num": 0,
      "brief": "耳熟！！ <br><br><a href=\"//emumo.xiami.com/apps/mobile\" target=\"_blank\">来自iPhone客户端</a>",
      "replies": []
    },
    {
      "author": {
        "id": "378832160",
        "name": "虾米用户",
        "motto": "虾米再见！永远爱你❤️",
        "link": "https://emumo.xiami.com/u/378832160",
        "photo_url": "https://pic.xiami.net/images/user/378832160/46682ec6177a446eb3493d6f8f1606f1_db507d3fbf1e4b66850fd46656526844.jpg@1e_1c_0i_1o_100Q_100w_100h"
      },
      "time": "2019-01-13 23:08",
      "ageree_num": 4,
      "disageree_num": 0,
      "brief": "记得那时候，骑个自行车从等红灯的车前拐过都会情不自禁的喊句“刀片超车”，真是的 <img src=\"//img.xiami.net/res/js/jquery/editor/sets/bbcode/images/smilies/default/401.png\"> <br><br><a href=\"//emumo.xiami.com/apps/mobile\" target=\"_blank\">来自android客户端</a>",
      "replies": []
    },
    {
      "author": {
        "id": "313343100",
        "name": "虾米用户",
        "motto": "",
        "link": "https://emumo.xiami.com/u/313343100",
        "photo_url": "https://pic.xiami.net/images/user/313343100/89eb4eadeba34b28b6aaf4c550316ec0_ac8331f9c8024ba898eba61a576f2344.jpg@1e_1c_0i_1o_100Q_100w_100h"
      },
      "time": "2019-01-11 23:38",
      "ageree_num": 3,
      "disageree_num": 0,
      "brief": "剑鲨巡航！漂移防火墙！ <br><br><a href=\"//emumo.xiami.com/apps/mobile\" target=\"_blank\">来自android客户端</a>",
      "replies": []
    },
    {
      "author": {
        "id": "244109779",
        "name": "虾米用户",
        "motto": "",
        "link": "https://emumo.xiami.com/u/244109779",
        "photo_url": "https://pic.xiami.net/images/avatar_new/48821478654104.jpg@1e_1c_0i_1o_100Q_100w_100h"
      },
      "time": "2019-01-11 22:29",
      "ageree_num": 1,
      "disageree_num": 0,
      "brief": "虽然我们不再同一地点，但是我们都在同一时间收看同一动画。 <br><br><a href=\"//emumo.xiami.com/apps/mobile\" target=\"_blank\">来自android客户端</a>",
      "replies": []
    },
    {
      "author": {
        "id": "74553388",
        "name": "虾米用户",
        "motto": "我心永恒",
        "link": "https://emumo.xiami.com/u/74553388",
        "photo_url": "https://pic.xiami.net/images/user/74553388/100620bf9e744535b45d89d1766fba74_3fd1c45a757642a2b86adb7b0bc7ba26.jpg@1e_1c_0i_1o_100Q_100w_100h"
      },
      "time": "2018-12-16 19:05",
      "ageree_num": 1,
      "disageree_num": 0,
      "brief": "旋风乱舞  神龙摆尾  刀片超车 <br><br><a href=\"//emumo.xiami.com/apps/mobile\" target=\"_blank\">来自android客户端</a>",
      "replies": []
    },
    {
      "author": {
        "id": "354853823",
        "name": "虾米用户",
        "motto": "聚散无常，别来无恙",
        "link": "https://emumo.xiami.com/u/354853823",
        "photo_url": "https://pic.xiami.net/images/user/354853823/4ad6911588cd4936bfb650be608c3bd7_123a30dd7365433286df1b98bec58593.jpg@1e_1c_0i_1o_100Q_100w_100h"
      },
      "time": "2018-12-15 16:56",
      "ageree_num": 1,
      "disageree_num": 0,
      "brief": "好歌没人听系列 <br><br><a href=\"//emumo.xiami.com/apps/mobile\" target=\"_blank\">来自android客户端</a>",
      "replies": []
    },
    {
      "author": {
        "id": "354853823",
        "name": "虾米用户",
        "motto": "聚散无常，别来无恙",
        "link": "https://emumo.xiami.com/u/354853823",
        "photo_url": "https://pic.xiami.net/images/user/354853823/4ad6911588cd4936bfb650be608c3bd7_123a30dd7365433286df1b98bec58593.jpg@1e_1c_0i_1o_100Q_100w_100h"
      },
      "time": "2018-11-15 20:40",
      "ageree_num": 2,
      "disageree_num": 0,
      "brief": "潘松和承包了我小时候的摇滚 <img src=\"//img.xiami.net/res/js/jquery/editor/sets/bbcode/images/smilies/default/402.png\"> <br><br><a href=\"//emumo.xiami.com/apps/mobile\" target=\"_blank\">来自android客户端</a>",
      "replies": []
    },
    {
      "author": {
        "id": "301061896",
        "name": "虾米用户",
        "motto": "努力热爱生活中",
        "link": "https://emumo.xiami.com/u/301061896",
        "photo_url": "https://pic.xiami.net/images/user/301061896/948a32d516394934931b5f03bc2becd8_18487ea3a6f54f07997643947a03e7f9.jpg@1e_1c_0i_1o_100Q_100w_100h"
      },
      "time": "2018-08-11 19:52",
      "ageree_num": 2,
      "disageree_num": 0,
      "brief": "老动漫就是给人在某个时期 就是突然想翻出来看看，看得津津有味 <br><br><a href=\"//emumo.xiami.com/apps/mobile\" target=\"_blank\">来自android客户端</a>",
      "replies": []
    },
    {
      "author": {
        "id": "400408004",
        "name": "虾米用户",
        "motto": "",
        "link": "https://emumo.xiami.com/u/400408004",
        "photo_url": "https://pic.xiami.net/images/avatar_new/1877728019_1533457886.jpg@1e_1c_0i_1o_100Q_100w_100h"
      },
      "time": "2018-08-07 19:12",
      "ageree_num": 1,
      "disageree_num": 0,
      "brief": "还行还行 <img src=\"//img.xiami.net/res/js/jquery/editor/sets/bbcode/images/smilies/default/415.png\"> <img src=\"//img.xiami.net/res/js/jquery/editor/sets/bbcode/images/smilies/default/415.png\"> <img src=\"//img.xiami.net/res/js/jquery/editor/sets/bbcode/images/smilies/default/415.png\"> <br><br><a href=\"//emumo.xiami.com/apps/mobile\" target=\"_blank\">来自android客户端</a>",
      "replies": []
    },
    {
      "author": {
        "id": "319688150",
        "name": "虾米用户",
        "motto": "愿经典不被遗忘",
        "link": "https://emumo.xiami.com/u/319688150",
        "photo_url": "https://pic.xiami.net/images/avatar_new/6393/5a6a34b647f42_319688150_b_w162h162_face_w162h162_x68y33w50h58c1.png@1e_1c_0i_1o_100Q_100w_100h"
      },
      "time": "2018-07-26 09:21",
      "ageree_num": 3,
      "disageree_num": 0,
      "brief": "童年哈 <br><br><a href=\"//emumo.xiami.com/apps/mobile\" target=\"_blank\">来自android客户端</a>",
      "replies": []
    },
    {
      "author": {
        "id": "304290274",
        "name": "虾米用户",
        "motto": "",
        "link": "https://emumo.xiami.com/u/304290274",
        "photo_url": "https://pic.xiami.net/images/avatar_new/222416801_1497363515.jpg@1e_1c_0i_1o_100Q_100w_100h"
      },
      "time": "2018-07-09 22:17",
      "ageree_num": 4,
      "disageree_num": 0,
      "brief": "人外有人，天外有天，闪电漂移，神龙摆尾，瞬间漂移，，，， <br><br><a href=\"//emumo.xiami.com/apps/mobile\" target=\"_blank\">来自android客户端</a>",
      "replies": []
    },
    {
      "author": {
        "id": "13691875",
        "name": "虾米用户",
        "motto": "谁的感叹 偶然合拍",
        "link": "https://emumo.xiami.com/u/13691875",
        "photo_url": "https://pic.xiami.net/images/user/13691875/701b0eec3d7e4863aeb5e87d221d47e5_438f25a762c04ff4bc7068c2331125ab.jpg@1e_1c_0i_1o_100Q_100w_100h"
      },
      "time": "2018-06-17 19:25",
      "ageree_num": 4,
      "disageree_num": 0,
      "brief": "跟小侄子一起看动漫频道听到的，真的很燃！！片尾曲也好听，但是不知道名字 <br><br><a href=\"//emumo.xiami.com/apps/mobile\" target=\"_blank\">来自android客户端</a>",
      "replies": []
    },
    {
      "author": {
        "id": "328243036",
        "name": "虾米用户",
        "motto": "青春不负我",
        "link": "https://emumo.xiami.com/u/328243036",
        "photo_url": "https://pic.xiami.net/images/avatar_new/6564/5ab48fb1f0362_328243036_b_w108h108.png@1e_1c_0i_1o_100Q_100w_100h"
      },
      "time": "2018-06-06 00:00",
      "ageree_num": 3,
      "disageree_num": 0,
      "brief": "童年记忆，闪电漂移，瞬间加速 <br><br><a href=\"//emumo.xiami.com/apps/mobile\" target=\"_blank\">来自android客户端</a>",
      "replies": []
    },
    {
      "author": {
        "id": "249966432",
        "name": "虾米用户",
        "motto": "生命没有了音乐，就如同是...",
        "link": "https://emumo.xiami.com/u/249966432",
        "photo_url": "https://pic.xiami.net/images/avatar_new/994074154_1480137614.jpg@1e_1c_0i_1o_100Q_100w_100h"
      },
      "time": "2018-05-29 13:07",
      "ageree_num": 4,
      "disageree_num": 0,
      "brief": "以前我玩QQ飞车的时候必听这歌。 <br><br><a href=\"//emumo.xiami.com/apps/mobile\" target=\"_blank\">来自android客户端</a>",
      "replies": []
    },
    {
      "author": {
        "id": "271358249",
        "name": "虾米用户",
        "motto": "历史是勇敢者和创造者！",
        "link": "https://emumo.xiami.com/u/271358249",
        "photo_url": "https://pic.xiami.net/images/avatar_new/5427/5a62135dd857a_271358249_1516376925.jpg@1e_1c_0i_1o_100Q_100w_100h"
      },
      "time": "2018-05-13 19:58",
      "ageree_num": 4,
      "disageree_num": 0,
      "brief": "厉害喽马爸爸，连这歌都能找见[带墨镜笑] <br><br><a href=\"//emumo.xiami.com/apps/mobile\" target=\"_blank\">来自iPhone客户端</a>",
      "replies": []
    },
    {
      "author": {
        "id": "344218010",
        "name": "虾米用户",
        "motto": "",
        "link": "https://emumo.xiami.com/u/344218010",
        "photo_url": "https://pic.xiami.net/images/user/344218010/5b069e18aac840039b639f2079ec7dc3_e0ae48add6db4fe2aa21cf709dd8e2a4.jpg@1e_1c_0i_1o_100Q_100w_100h"
      },
      "time": "2018-05-08 08:11",
      "ageree_num": 3,
      "disageree_num": 0,
      "brief": "这部动画片会不会抄袭四驱兄弟啊？？？ <br><br><a href=\"//emumo.xiami.com/apps/mobile\" target=\"_blank\">来自android客户端</a>",
      "replies": [
        {
          "author": {
            "id": "307467833",
            "name": "虾米用户",
            "motto": "夜幕降临、满天星辰、思念...",
            "link": "https://emumo.xiami.com/u/307467833",
            "photo_url": "https://pic.xiami.net/images/user/307467833/0a4678197fb34854b07b7257b864eed3_6f65ae7350fe4577b2c87c37f604c56b.jpg@1e_1c_0i_1o_100Q_100w_100h"
          },
          "time": "2018-05-23 00:07",
          "ageree_num": 0,
          "disageree_num": 0,
          "brief": "有点像 <img src=\"//img.xiami.net/res/js/jquery/editor/sets/bbcode/images/smilies/default/403.png\"> <br><br><a href=\"//emumo.xiami.com/apps/mobile\" target=\"_blank\">来自android客户端</a>",
          "replies": []
        }
      ]
    },
    {
      "author": {
        "id": "340119787",
        "name": "虾米用户",
        "motto": "",
        "link": "https://emumo.xiami.com/u/340119787",
        "photo_url": "https://pic.xiami.net/images/default/xiami_8/avatar_new_3x.png@1e_1c_0i_1o_100Q_100w_100h"
      },
      "time": "2018-05-05 15:25",
      "ageree_num": 2,
      "disageree_num": 0,
      "brief": "刀片超车 <br><br><a href=\"//emumo.xiami.com/apps/mobile\" target=\"_blank\">来自android客户端</a>",
      "replies": []
    },
    {
      "author": {
        "id": "275938786",
        "name": "虾米用户",
        "motto": "",
        "link": "https://emumo.xiami.com/u/275938786",
        "photo_url": "https://pic.xiami.net/images/avatar_new/5518/5ad1743c75199_275938786_b_w240h240_face_w240h240_x87y88w84h117c1.png@1e_1c_0i_1o_100Q_100w_100h"
      },
      "time": "2018-04-10 19:56",
      "ageree_num": 2,
      "disageree_num": 0,
      "brief": "神龙摆尾 <br><br><a href=\"//emumo.xiami.com/apps/mobile\" target=\"_blank\">来自android客户端</a>",
      "replies": []
    },
    {
      "author": {
        "id": "302036763",
        "name": "虾米用户",
        "motto": "",
        "link": "https://emumo.xiami.com/u/302036763",
        "photo_url": "https://pic.xiami.net/images/avatar_new/937654633_1496637267.jpg@1e_1c_0i_1o_100Q_100w_100h"
      },
      "time": "2018-04-04 21:44",
      "ageree_num": 4,
      "disageree_num": 0,
      "brief": "奥迪双钻 <br><br><a href=\"//emumo.xiami.com/apps/mobile\" target=\"_blank\">来自android客户端</a>",
      "replies": []
    },
    {
      "author": {
        "id": "314891382",
        "name": "虾米用户",
        "motto": "",
        "link": "https://emumo.xiami.com/u/314891382",
        "photo_url": "https://pic.xiami.net/images/avatar_new/6297/5a881d48da71e_314891382_b_w108h108.png@1e_1c_0i_1o_100Q_100w_100h"
      },
      "time": "2018-02-12 19:26",
      "ageree_num": 2,
      "disageree_num": 0,
      "brief": "小学五年级 <br><br><a href=\"//emumo.xiami.com/apps/mobile\" target=\"_blank\">来自android客户端</a>",
      "replies": []
    },
    {
      "author": {
        "id": "191534381",
        "name": "虾米用户",
        "motto": "过了",
        "link": "https://emumo.xiami.com/u/191534381",
        "photo_url": "https://pic.xiami.net/images/user/191534381/33209daef3774436856f80b406450139_0f19134cd77e4b22a9b3c11e619ae86e.jpg@1e_1c_0i_1o_100Q_100w_100h"
      },
      "time": "2018-02-05 14:33",
      "ageree_num": 3,
      "disageree_num": 0,
      "brief": "qq飞车 <br><br><a href=\"//emumo.xiami.com/apps/mobile\" target=\"_blank\">来自android客户端</a>",
      "replies": []
    },
    {
      "author": {
        "id": "276376482",
        "name": "虾米用户",
        "motto": "有一天我可以说：我生已尽...",
        "link": "https://emumo.xiami.com/u/276376482",
        "photo_url": "https://pic.xiami.net/images/avatar_new/5527/59495b04bd483_276376482_b_w120h122_face_w120h122_x51y36w37h48c1.png@1e_1c_0i_1o_100Q_100w_100h"
      },
      "time": "2018-01-03 23:39",
      "ageree_num": 4,
      "disageree_num": 0,
      "brief": "刀片超车 <br><br><a href=\"//emumo.xiami.com/apps/mobile\" target=\"_blank\">来自android客户端</a>",
      "replies": []
    },
    {
      "author": {
        "id": "253827743",
        "name": "虾米用户",
        "motto": "",
        "link": "https://emumo.xiami.com/u/253827743",
        "photo_url": "https://pic.xiami.net/default_avatar_2016_100.jpg@1e_1c_0i_1o_100Q_100w_100h"
      },
      "time": "2017-12-07 09:27",
      "ageree_num": 4,
      "disageree_num": 0,
      "brief": "00后的童年之一 <br><br><a href=\"//emumo.xiami.com/apps/mobile\" target=\"_blank\">来自iPhone客户端</a>",
      "replies": []
    },
    {
      "author": {
        "id": "328270005",
        "name": "虾米用户",
        "motto": "",
        "link": "https://emumo.xiami.com/u/328270005",
        "photo_url": "https://pic.xiami.net/images/avatar_new/504133155_1507039723.jpg@1e_1c_0i_1o_100Q_100w_100h"
      },
      "time": "2017-11-19 19:25",
      "ageree_num": 12,
      "disageree_num": 0,
      "brief": "看结局他们一起冲线的时候热血澎湃 <br><br><a href=\"//emumo.xiami.com/apps/mobile\" target=\"_blank\">来自android客户端</a>",
      "replies": []
    },
    {
      "author": {
        "id": "233152636",
        "name": "虾米用户",
        "motto": "MICHAEL",
        "link": "https://emumo.xiami.com/u/233152636",
        "photo_url": "https://pic.xiami.net/images/avatar_new/4663/5a33aab0a9ee1_233152636_b_w162h162.png@1e_1c_0i_1o_100Q_100w_100h"
      },
      "time": "2017-11-17 22:46",
      "ageree_num": 11,
      "disageree_num": 0,
      "brief": "07年的回忆，那年我五岁 <br><br><a href=\"//emumo.xiami.com/apps/mobile\" target=\"_blank\">来自android客户端</a>",
      "replies": [
        {
          "author": {
            "id": "210630886",
            "name": "虾米用户",
            "motto": "❤",
            "link": "https://emumo.xiami.com/u/210630886",
            "photo_url": "https://pic.xiami.net/images/user/210630886/673cc35cb5cf4292a3d4e0e9d10ce65e_60fe09dd214f4cf89edcbf297a4fe3c3.jpg@1e_1c_0i_1o_100Q_100w_100h"
          },
          "time": "2019-01-09 00:35",
          "ageree_num": 0,
          "disageree_num": 0,
          "brief": "咋俩差不多同岁 <br><br><a href=\"//emumo.xiami.com/apps/mobile\" target=\"_blank\">来自android客户端</a>",
          "replies": []
        }
      ]
    },
    {
      "author": {
        "id": "12836394",
        "name": "虾米用户",
        "motto": "",
        "link": "https://emumo.xiami.com/u/12836394",
        "photo_url": "https://pic.xiami.net/images/avatar_new/256/59691080cf68c_12836394_b_w108h108.png@1e_1c_0i_1o_100Q_100w_100h"
      },
      "time": "2017-11-02 14:36",
      "ageree_num": 6,
      "disageree_num": 0,
      "brief": "熟悉的口音，熟悉的调子 <br><br><a href=\"//emumo.xiami.com/apps/mobile\" target=\"_blank\">来自android客户端</a>",
      "replies": []
    },
    {
      "author": {
        "id": "279592735",
        "name": "虾米用户",
        "motto": "",
        "link": "https://emumo.xiami.com/u/279592735",
        "photo_url": "https://pic.xiami.net/images/user/279592735/65950f7117d842db9268de6dfc959b3b_fc012c2ff5d041b6ae7996f014cc342f.jpg@1e_1c_0i_1o_100Q_100w_100h"
      },
      "time": "2017-10-30 21:32",
      "ageree_num": 27,
      "disageree_num": 0,
      "brief": "最后两句很励志，没人觉得吗？",
      "replies": []
    },
    {
      "author": {
        "id": "222957917",
        "name": "虾米用户",
        "motto": " ",
        "link": "https://emumo.xiami.com/u/222957917",
        "photo_url": "https://pic.xiami.net/images/avatar_new/4459/5944680fc47a4_222957917_1497655311.jpg@1e_1c_0i_1o_100Q_100w_100h"
      },
      "time": "2017-10-29 09:02",
      "ageree_num": 3,
      "disageree_num": 0,
      "brief": "雷龙破风 <br><br><a href=\"//emumo.xiami.com/apps/mobile\" target=\"_blank\">来自iPhone客户端</a>",
      "replies": []
    },
    {
      "author": {
        "id": "190461052",
        "name": "虾米用户",
        "motto": "爱过你  人生已被成全",
        "link": "https://emumo.xiami.com/u/190461052",
        "photo_url": "https://pic.xiami.net/images/avatar_new/3809/594e961e18403_190461052_1498322462.jpg@1e_1c_0i_1o_100Q_100w_100h"
      },
      "time": "2017-10-09 23:22",
      "ageree_num": 4,
      "disageree_num": 0,
      "brief": "直捣黄龙 <br><br><a href=\"//emumo.xiami.com/apps/mobile\" target=\"_blank\">来自iPhone客户端</a>",
      "replies": []
    },
    {
      "author": {
        "id": "50461586",
        "name": "虾米用户",
        "motto": " ",
        "link": "https://emumo.xiami.com/u/50461586",
        "photo_url": "https://pic.xiami.net/images/user/50461586/ab90656a3d204927b197d2a627c8c882_9175466febc848f3a42207f380227ffb.jpg@1e_1c_0i_1o_100Q_100w_100h"
      },
      "time": "2017-09-29 21:50",
      "ageree_num": 4,
      "disageree_num": 0,
      "brief": "刀片超车 <br><br><a href=\"//emumo.xiami.com/apps/mobile\" target=\"_blank\">来自android客户端</a>",
      "replies": []
    },
    {
      "author": {
        "id": "237649394",
        "name": "虾米用户",
        "motto": "",
        "link": "https://emumo.xiami.com/u/237649394",
        "photo_url": "https://pic.xiami.net/images/default/xiami_8/avatar_new_3x.png@1e_1c_0i_1o_100Q_100w_100h"
      },
      "time": "2017-09-13 16:09",
      "ageree_num": 41,
      "disageree_num": 0,
      "brief": "如果我听不懂歌词，这也是一首燃曲了，虽说也确实很燃了 <img src=\"//img.xiami.net/res/js/jquery/editor/sets/bbcode/images/smilies/default/402.png\"> <br><br><a href=\"//emumo.xiami.com/apps/mobile\" target=\"_blank\">来自android客户端</a>",
      "replies": [
        {
          "author": {
            "id": "279842573",
            "name": "虾米用户",
            "motto": "有光兮，其四方……谁还不...",
            "link": "https://emumo.xiami.com/u/279842573",
            "photo_url": "https://pic.xiami.net/images/avatar_new/5596/5bc30aa8a71fd_279842573_b_w162h162.png@1e_1c_0i_1o_100Q_100w_100h"
          },
          "time": "2019-04-19 21:53",
          "ageree_num": 0,
          "disageree_num": 0,
          "brief": "听不懂歌词 <img src=\"//img.xiami.net/res/js/jquery/editor/sets/bbcode/images/smilies/default/400.png\"><br>兄弟，你刚来中国 <img src=\"//img.xiami.net/res/js/jquery/editor/sets/bbcode/images/smilies/default/429.png\"> <br><br><a href=\"//emumo.xiami.com/apps/mobile\" target=\"_blank\">来自android客户端</a>",
          "replies": []
        }
      ]
    },
    {
      "author": {
        "id": "237649394",
        "name": "虾米用户",
        "motto": "",
        "link": "https://emumo.xiami.com/u/237649394",
        "photo_url": "https://pic.xiami.net/images/default/xiami_8/avatar_new_3x.png@1e_1c_0i_1o_100Q_100w_100h"
      },
      "time": "2017-09-13 16:08",
      "ageree_num": 16,
      "disageree_num": 0,
      "brief": "为什么是儿歌分类？！ <img src=\"//img.xiami.net/res/js/jquery/editor/sets/bbcode/images/smilies/default/402.png\"> <img src=\"//img.xiami.net/res/js/jquery/editor/sets/bbcode/images/smilies/default/402.png\"> <img src=\"//img.xiami.net/res/js/jquery/editor/sets/bbcode/images/smilies/default/402.png\"> <br><br><a href=\"//emumo.xiami.com/apps/mobile\" target=\"_blank\">来自android客户端</a>",
      "replies": [
        {
          "author": {
            "id": "222957917",
            "name": "虾米用户",
            "motto": " ",
            "link": "https://emumo.xiami.com/u/222957917",
            "photo_url": "https://pic.xiami.net/images/avatar_new/4459/5944680fc47a4_222957917_1497655311.jpg@1e_1c_0i_1o_100Q_100w_100h"
          },
          "time": "2017-10-20 21:59",
          "ageree_num": 0,
          "disageree_num": 0,
          "brief": "因为这是一部动画片的主题曲 <img src=\"//img.xiami.net/res/js/jquery/editor/sets/bbcode/images/smilies/default/400.png\"> <br><br><a href=\"//emumo.xiami.com/apps/mobile\" target=\"_blank\">来自iPhone客户端</a>",
          "replies": []
        }
      ]
    },
    {
      "author": {
        "id": "203964706",
        "name": "虾米用户",
        "motto": "青春该奋斗",
        "link": "https://emumo.xiami.com/u/203964706",
        "photo_url": "https://pic.xiami.net/images/avatar_new/4079/59fe6b49a57c6_203964706_b_w108h108.png@1e_1c_0i_1o_100Q_100w_100h"
      },
      "time": "2017-08-18 19:39",
      "ageree_num": 14,
      "disageree_num": 0,
      "brief": "闪电漂移~！！！！ <img src=\"//img.xiami.net/res/js/jquery/editor/sets/bbcode/images/smilies/default/401.png\"> <br><br><a href=\"//emumo.xiami.com/apps/mobile\" target=\"_blank\">来自android客户端</a>",
      "replies": [
        {
          "author": {
            "id": "210630886",
            "name": "虾米用户",
            "motto": "❤",
            "link": "https://emumo.xiami.com/u/210630886",
            "photo_url": "https://pic.xiami.net/images/user/210630886/673cc35cb5cf4292a3d4e0e9d10ce65e_60fe09dd214f4cf89edcbf297a4fe3c3.jpg@1e_1c_0i_1o_100Q_100w_100h"
          },
          "time": "2019-01-09 00:36",
          "ageree_num": 0,
          "disageree_num": 0,
          "brief": "神龙摆尾，还有个鲨鱼啥的， <br><br><a href=\"//emumo.xiami.com/apps/mobile\" target=\"_blank\">来自android客户端</a>",
          "replies": []
        }
      ]
    },
    {
      "author": {
        "id": "214542942",
        "name": "虾米用户",
        "motto": "",
        "link": "https://emumo.xiami.com/u/214542942",
        "photo_url": "https://pic.xiami.net/images/avatar_new/4290/58493f9bd60da_214542942_1481195419.png@1e_1c_0i_1o_100Q_100w_100h"
      },
      "time": "2017-08-08 20:28",
      "ageree_num": 9,
      "disageree_num": 0,
      "brief": "雷速登！冲啊 <br><br><a href=\"//emumo.xiami.com/apps/mobile\" target=\"_blank\">来自android客户端</a>",
      "replies": []
    },
    {
      "author": {
        "id": "16518540",
        "name": "虾米用户",
        "motto": "",
        "link": "https://emumo.xiami.com/u/16518540",
        "photo_url": "https://pic.xiami.net/images/avatar_new/330/5992b647d92b8_16518540_b_w189h189.png@1e_1c_0i_1o_100Q_100w_100h"
      },
      "time": "2017-07-12 20:31",
      "ageree_num": 18,
      "disageree_num": 0,
      "brief": "刀片超车 <br><br><a href=\"//emumo.xiami.com/apps/mobile\" target=\"_blank\">来自android客户端</a>",
      "replies": []
    },
    {
      "author": {
        "id": "294685137",
        "name": "虾米用户",
        "motto": "",
        "link": "https://emumo.xiami.com/u/294685137",
        "photo_url": "https://pic.xiami.net/images/avatar_new/5893/594f92bb3a4f5_294685137_b_w162h162.png@1e_1c_0i_1o_100Q_100w_100h"
      },
      "time": "2017-06-21 22:30",
      "ageree_num": 48,
      "disageree_num": 0,
      "brief": "记不清了，大概小学五六年级时，超喜欢这部动画片。现在大二了，再从腾讯中翻出来，还是比较喜欢，只是没有儿时那种那么激动的心情了。犹记那个夏天的暑假，几个小伙伴围在电视机前专注的看着，里面的人物每喊出一种技能，都会心头一振，热血澎湃。超兴奋超开心的 <img src=\"//img.xiami.net/res/js/jquery/editor/sets/bbcode/images/smilies/default/401.png\"> <img src=\"//img.xiami.net/res/js/jquery/editor/sets/bbcode/images/smilies/default/401.png\"> <img src=\"//img.xiami.net/res/js/jquery/editor/sets/bbcode/images/smilies/default/401.png\"> <br><br><a href=\"//emumo.xiami.com/apps/mobile\" target=\"_blank\">来自android客户端</a>",
      "replies": [
        {
          "author": {
            "id": "414500161",
            "name": "虾米用户",
            "motto": "没得签名",
            "link": "https://emumo.xiami.com/u/414500161",
            "photo_url": "https://pic.xiami.net/images/user/414500161/9521367cb6574d59ad2daad532bfad96_a07c4ec3720e4c1a9c6db08c064dc9bc.jpg@1e_1c_0i_1o_100Q_100w_100h"
          },
          "time": "2019-05-17 18:36",
          "ageree_num": 0,
          "disageree_num": 0,
          "brief": "犹如一阵清风吹过 <br><br><a href=\"//emumo.xiami.com/apps/mobile\" target=\"_blank\">来自android客户端</a>",
          "replies": []
        },
        {
          "author": {
            "id": "376428812",
            "name": "虾米用户",
            "motto": "",
            "link": "https://emumo.xiami.com/u/376428812",
            "photo_url": "https://pic.xiami.net/images/default/xiami_8/avatar_new_3x.png@1e_1c_0i_1o_100Q_100w_100h"
          },
          "time": "2020-01-30 11:44",
          "ageree_num": 0,
          "disageree_num": 0,
          "brief": "咱们岁数差不多 <br><br><a href=\"//emumo.xiami.com/apps/mobile\" target=\"_blank\">来自android客户端</a>",
          "replies": []
        }
      ]
    },
    {
      "author": {
        "id": "266661144",
        "name": "虾米用户",
        "motto": "花开两朵，天各一方",
        "link": "https://emumo.xiami.com/u/266661144",
        "photo_url": "https://pic.xiami.net/images/avatar_new/5333/58a4634deaa32_266661144_b_w108h108.png@1e_1c_0i_1o_100Q_100w_100h"
      },
      "time": "2017-05-30 23:19",
      "ageree_num": 17,
      "disageree_num": 0,
      "brief": "我还是最喜欢看第一部 <br><br><a href=\"//emumo.xiami.com/apps/mobile\" target=\"_blank\">来自android客户端</a>",
      "replies": []
    },
    {
      "author": {
        "id": "251096897",
        "name": "虾米用户",
        "motto": "爱你不懂",
        "link": "https://emumo.xiami.com/u/251096897",
        "photo_url": "https://pic.xiami.net/images/avatar_new/5021/59372882bba43_251096897_b_w162h162.png@1e_1c_0i_1o_100Q_100w_100h"
      },
      "time": "2017-05-18 13:17",
      "ageree_num": 3,
      "disageree_num": 0,
      "brief": "这么少的人 <br><br><a href=\"//emumo.xiami.com/apps/mobile\" target=\"_blank\">来自android客户端</a>",
      "replies": []
    },
    {
      "author": {
        "id": "296843640",
        "name": "虾米用户",
        "motto": "",
        "link": "https://emumo.xiami.com/u/296843640",
        "photo_url": "https://pic.xiami.net/images/avatar_new/5936/591bd3bea8da0_296843640_b_w162h162.png@1e_1c_0i_1o_100Q_100w_100h"
      },
      "time": "2017-05-16 21:42",
      "ageree_num": 3,
      "disageree_num": 0,
      "brief": "那些逝去的童年光阴 过了这么久听鼻子突然一酸 <br><br><a href=\"//emumo.xiami.com/apps/mobile\" target=\"_blank\">来自android客户端</a>",
      "replies": []
    },
    {
      "author": {
        "id": "38491690",
        "name": "虾米用户",
        "motto": " ",
        "link": "https://emumo.xiami.com/u/38491690",
        "photo_url": "https://pic.xiami.net/images/avatar_new/769/5ad6ee9dab204_38491690_1524035229.jpg@1e_1c_0i_1o_100Q_100w_100h"
      },
      "time": "2017-05-11 08:34",
      "ageree_num": 2,
      "disageree_num": 0,
      "brief": "和迪迦奥特曼的奇迹再现是绝配啊 <br><br><a href=\"//emumo.xiami.com/apps/mobile\" target=\"_blank\">来自iPhone客户端</a>",
      "replies": []
    },
    {
      "author": {
        "id": "204868426",
        "name": "虾米用户",
        "motto": "",
        "link": "https://emumo.xiami.com/u/204868426",
        "photo_url": "https://pic.xiami.net/images/avatar_new/4097/58fa275b0a6d1_204868426_b_w182h182_face_w182h182_x87y43w38h49c1.png@1e_1c_0i_1o_100Q_100w_100h"
      },
      "time": "2017-04-22 22:07",
      "ageree_num": 2,
      "disageree_num": 0,
      "brief": "雷速登闪电⚡ <img src=\"//img.xiami.net/res/js/jquery/editor/sets/bbcode/images/smilies/default/402.png\"> <img src=\"//img.xiami.net/res/js/jquery/editor/sets/bbcode/images/smilies/default/402.png\"> <img src=\"//img.xiami.net/res/js/jquery/editor/sets/bbcode/images/smilies/default/402.png\"> <img src=\"//img.xiami.net/res/js/jquery/editor/sets/bbcode/images/smilies/default/402.png\"> <br><br><a href=\"//emumo.xiami.com/apps/mobile\" target=\"_blank\">来自android客户端</a>",
      "replies": []
    }
  ]
}